Workbook
Name Anniversaire: TAM!$B$27:$F$27,TAM!$B$39:$F$39,TAM!$B$51:$F$51,TAM!$B$63:$F$63
Name CAP1E: TAM!$S$6
Name CapitFIXE: TAM!#REF!
Name Changement_de_taux: TAM!$B$15:$B$315
Name Cout_Total: TAM!$P$8
Name DATDB: TAM!$S$7
Name DebAmort: TAM!$F$6
Name Différé: TAM!$V$8
Name DiffSimple: TAM!$V$6
Name DiffTotal: TAM!$V$7
Name EchFIXE: TAM!$S$2
Name FraisF: TAM!$M$3
Name FraisV: TAM!$M$4
Name Ijour: TAM!$T$6
Name Imois: TAM!$T$5
Name INT1E: TAM!$S$5
Name Jour1: TAM!$T$7
Name Jour2: TAM!$T$8
Name MoisD: TAM!$T$9
Name MtEch: TAM!$D$8
Name MtEmprunt: TAM!$V$12
Name NbDeci: TAM!$S$1
Name NbEch: TAM!$T$2
Name NbEchAn: TAM!$T$1
Name NoEchMaxi: TAM!$S$3
Name NoEchRemb: TAM!$S$4
Name Nombre_échéances: TAM!$P$4
Name Periodicite: TAM!$W$10
Name RVDebit: TAM!#REF!
Name TauxActuariel: TAM!$V$3
Name Total_Capital: TAM!$P$6
Name Total_Frais: TAM!$P$7
Name Total_Intérêts: TAM!$P$5
Name TVDebit: TAM!$B$2:$B$8
Name TxPer: TAM!$T$4

Sheet TAM
S1: =IF(ISERROR(Avancé!D3),2,Avancé!D3) | T1: =IF(Periodicite="M",12)+IF(Periodicite="T",4)+IF(Periodicite="S",2)+IF(Periodicite="A",1)+IF(Periodicite="H",52)+IF(Periodicite="Q",26)+IF(Periodicite="B",24) | U1: Nombre échéance par an | V1: Type Taux | W1: Periodicité
B2: Caractéristiques | K2: Frais | N2: Récapitulatif | S2: =IF(ISERROR(Avancé!I9),TRUE,IF(Avancé!I9=1,TRUE,FALSE)) | T2: =T3*NbEchAn/12 | U2: Nombre échéance total | V2: 2 | W2: 1
C3: Montant emprunté : | D3: 80000 | E3: durée : | F3: 15 | G3: ans | K3: Frais Fixe (ADI) / ech | N3: Date dernière échéance | P3: =MAX(K14:K447) | S3: =IF(ISERROR(Avancé!D17),99999,Avancé!D17) | T3: =F3*12+F4 | U3: Durée totale (en mois) | V3: =V2=1 | W3: Mensuel
E4: et | F4: 11 | G4: mois | K4: Frais variable (en %CRD) | N4: Nombre échéances | P4: =MAX(H14:H447) | S4: =IF(ISERROR(Avancé!E17),99999,Avancé!E17) | T4: =IF(TauxActuariel,((D5+1)^(1/NbEchAn))-1,D5/NbEchAn) | U4: Taux période | V4: Différé | W4: Trimestriel
C5: Taux annuel : | D5: 0.1 | F5: 1° échéance : | H5: Périodicité : | K5: Différé | N5: Total Intérêts | P5: =SUM(M14:M447) | S5: =IF(1<=NoEchMaxi, IF(ISERROR(Avancé!D37),ROUND(L15*R15,NbDeci),Avancé!D37), 0) | T5: =0+IF(Periodicite="M",1)+IF(Periodicite="T",3)+IF(Periodicite="S",6)+IF(Periodicite="A",12)+IF(Periodicite="B",0.5) | U5: IntervalMois | V5: 1 | W5: Semestriel
F6: 46128 | N6: Total Capital | P6: =SUM(N14:N447)-SUMIF(C14:C447,"<0") | S6: =IF(1>NoEchMaxi, 0, IF(ISERROR(Avancé!E37), IF(1<=Différé,IF(DiffTotal,-INT1E,0),IF(1>=NoEchRemb,L15,IF(S15-(M15*EchFIXE)>L15-2,L15,S15-(M15*EchFIXE))))+C15, Avancé!E37)) | T6: =0+IF(Periodicite="H",7)+IF(Periodicite="Q",14) | U6: IntervalJour | V6: =IF(Différé>0,V5=1,FALSE) | W6: Annuel
K7: Nombre de mois différé | M7: 0 | N7: Total Frais | P7: =SUM(O14:O447) | S7: =IF(ISERROR(Avancé!C37), IF(Ijour=0,MIN(DATE(YEAR(DebAmort),MONTH(DebAmort)-MoisD-Imois,Jour2),DATE(YEAR(DebAmort),MONTH(DebAmort)-MoisD+1-Imois,0)),DATE(YEAR(DebAmort),MONTH(DebAmort),Jour1-Ijour)), Avancé!C37) | T7: =DAY(DebAmort) | U7: J1 | V7: =IF(Différé>0,V5=2,FALSE) | W7: Hebdomadaire
C8: =IF(EchFIXE,"Montant échéance fixe :","Capital / échéance :") | D8: =IF(OR(D5=0,NOT(EchFIXE)),ROUND(MtEmprunt/NbEch,NbDeci),ROUND(MtEmprunt*TxPer/(1-((1+TxPer)^-NbEch)),NbDeci)) | K8: Déblocage initial | N8: Coût total crédit | P8: =SUM(P5:P7) | T8: =IF(Periodicite="B",IF(T7>15,MIN(T7-15,15),T7+15),T7) | U8: J2 | V8: =M7*NbEchAn/12 | W8: Quinzaine
T9: =IF(Jour2<Jour1,1,0) | U9: M1 | V9: MtEmprunt | W9: Bimensuel
B10: Opération | H10: Tableau d'amortissement | R10: Données recalcul | V10: =D3 | W10: =UPPER(LEFT(INDEX(W3:W9,W2,1)))
B11: =COUNTIF(B15:B447,">0") | C11: =COUNTIF(C15:C447,">0")+COUNTIF(C15:C447,"<0") | D11: =COUNTIF(D15:D447,">0") | E11: =COUNTIF(E15:E447,">0") | F11: =COUNTIF(F14:F447,">0") | I11: Reste sur initial | K11: Date Échéance | L11: Capital restant dû | M11: Intérêts payés | N11: Capital remboursé | O11: Montant des Frais | P11: Total payé | R11: Taux période | S11: Montant échéance | V11: =INDEX(L15:L996,Différé+1,1)
B12: Nouveau Taux | C12: Capital remboursé | D12: Nouveau Nb d'échéance | E12: Nouvelle échéance | F12: Frais opération | H12: N° | J12: Année | V12: =IF(DiffTotal,V11,V10)
H13: Ech
C14: =IF(M8>0,-M8,-D3) | D14: Déblocage initial | H14: 0 | J14: =IF(ISNUMBER(K14),YEAR(K14),"") | K14: =DATDB | L14: 0 | N14: =C14 | O14: =F14 | P14: =SUM(M14:O14)
H15: =IF(L15=0,"",H14+1) | I15: =IF(L15>0,NbEch+Différé+1-H15,"") | J15: =IF(ISNUMBER(K15),YEAR(K15),"") | K15: =DATE(YEAR(DebAmort),MONTH(DebAmort),DAY(DebAmort)) | L15: =L14-N14 | M15: =INT1E | N15: =CAP1E+C15 | O15: =IF(OR(L15=0,H15>NoEchMaxi),0,ROUND(FraisF+FraisV*L15,NbDeci))+F15 | P15: =SUM(M15:O15) | R15: =IF(B15>0,IF(TauxActuariel,((B15+1)^(1/NbEchAn))-1,B15/NbEchAn),TxPer) | S15: =IF(E15>0,E15,IF(D15>0,IF(AND(EchFIXE,R15>0),ROUND((L15-C15)*R15/(1-((1+R15)^-D15)),NbDeci),ROUND(L15/D15,NbDeci)),MtEch))
H16: =IF(L16=0,"",H15+1) | I16: =IF(L16>0,NbEch+Différé+1-H16,"") | J16: =IF(ISNUMBER(K16),YEAR(K16),"") | K16: =IF(L16=0,"",IF(Ijour=0,MIN(DATE(YEAR(DebAmort),MONTH(DebAmort)+MoisD+(H16-1)*Imois,Jour2),DATE(YEAR(DebAmort),MONTH(DebAmort)+MoisD+1+(H16-1)*Imois,0)),DATE(YEAR(DebAmort),MONTH(DebAmort),Jour1+(H16-1)*Ijour))) | L16: =L15-N15 | M16: =IF(H16<=NoEchMaxi,ROUND(L16*R16,NbDeci),0) | N16: =IF(OR(H16<=Différé,H16>NoEchMaxi),IF(DiffTotal,-M16,0),IF(H16>=NoEchRemb,L16,IF(S16-(M16*EchFIXE)>L16-2,L16,S16-(M16*EchFIXE))))+C16 | O16: =IF(OR(L16=0,H16>NoEchMaxi),0,ROUND(FraisF+FraisV*L16,NbDeci))+F16 | P16: =SUM(M16:O16) | R16: =IF(B16>0,IF(TauxActuariel,((B16+1)^(1/NbEchAn))-1,B16/NbEchAn),R15) | S16: =IF(E16>0,E16,IF(D16>0,IF(AND(EchFIXE,R16>0),ROUND((L16-C16)*R16/(1-((1+R16)^-D16)),NbDeci),ROUND(L16/D16,NbDeci)),S15))
H17: =IF(L17=0,"",H16+1) | I17: =IF(L17>0,NbEch+Différé+1-H17,"") | J17: =IF(ISNUMBER(K17),YEAR(K17),"") | K17: =IF(L17=0,"",IF(Ijour=0,MIN(DATE(YEAR(DebAmort),MONTH(DebAmort)+(H17-1)*Imois,Jour1),DATE(YEAR(DebAmort),MONTH(DebAmort)+1+(H17-1)*Imois,0)),DATE(YEAR(DebAmort),MONTH(DebAmort),Jour1+(H17-1)*Ijour))) | L17: =L16-N16 | M17: =IF(H17<=NoEchMaxi,ROUND(L17*R17,NbDeci),0) | N17: =IF(OR(H17<=Différé,H17>NoEchMaxi),IF(DiffTotal,-M17,0),IF(H17>=NoEchRemb,L17,IF(S17-(M17*EchFIXE)>L17-2,L17,S17-(M17*EchFIXE))))+C17 | O17: =IF(OR(L17=0,H17>NoEchMaxi),0,ROUND(FraisF+FraisV*L17,NbDeci))+F17 | P17: =SUM(M17:O17) | R17: =IF(B17>0,IF(TauxActuariel,((B17+1)^(1/NbEchAn))-1,B17/NbEchAn),R16) | S17: =IF(E17>0,E17,IF(D17>0,IF(AND(EchFIXE,R17>0),ROUND((L17-C17)*R17/(1-((1+R17)^-D17)),NbDeci),ROUND(L17/D17,NbDeci)),S16))
H18: =IF(L18=0,"",H17+1) | I18: =IF(L18>0,NbEch+Différé+1-H18,"") | J18: =IF(ISNUMBER(K18),YEAR(K18),"") | K18: =IF(L18=0,"",IF(Ijour=0,MIN(DATE(YEAR(DebAmort),MONTH(DebAmort)+MoisD+(H18-1)*Imois,Jour2),DATE(YEAR(DebAmort),MONTH(DebAmort)+MoisD+1+(H18-1)*Imois,0)),DATE(YEAR(DebAmort),MONTH(DebAmort),Jour1+(H18-1)*Ijour))) | L18: =L17-N17 | M18: =IF(H18<=NoEchMaxi,ROUND(L18*R18,NbDeci),0) | N18: =IF(OR(H18<=Différé,H18>NoEchMaxi),IF(DiffTotal,-M18,0),IF(H18>=NoEchRemb,L18,IF(S18-(M18*EchFIXE)>L18-2,L18,S18-(M18*EchFIXE))))+C18 | O18: =IF(OR(L18=0,H18>NoEchMaxi),0,ROUND(FraisF+FraisV*L18,NbDeci))+F18 | P18: =SUM(M18:O18) | R18: =IF(B18>0,IF(TauxActuariel,((B18+1)^(1/NbEchAn))-1,B18/NbEchAn),R17) | S18: =IF(E18>0,E18,IF(D18>0,IF(AND(EchFIXE,R18>0),ROUND((L18-C18)*R18/(1-((1+R18)^-D18)),NbDeci),ROUND(L18/D18,NbDeci)),S17))
H19: =IF(L19=0,"",H18+1) | I19: =IF(L19>0,NbEch+Différé+1-H19,"") | J19: =IF(ISNUMBER(K19),YEAR(K19),"") | K19: =IF(L19=0,"",IF(Ijour=0,MIN(DATE(YEAR(DebAmort),MONTH(DebAmort)+(H19-1)*Imois,Jour1),DATE(YEAR(DebAmort),MONTH(DebAmort)+1+(H19-1)*Imois,0)),DATE(YEAR(DebAmort),MONTH(DebAmort),Jour1+(H19-1)*Ijour))) | L19: =L18-N18 | M19: =IF(H19<=NoEchMaxi,ROUND(L19*R19,NbDeci),0) | N19: =IF(OR(H19<=Différé,H19>NoEchMaxi),IF(DiffTotal,-M19,0),IF(H19>=NoEchRemb,L19,IF(S19-(M19*EchFIXE)>L19-2,L19,S19-(M19*EchFIXE))))+C19 | O19: =IF(OR(L19=0,H19>NoEchMaxi),0,ROUND(FraisF+FraisV*L19,NbDeci))+F19 | P19: =SUM(M19:O19) | R19: =IF(B19>0,IF(TauxActuariel,((B19+1)^(1/NbEchAn))-1,B19/NbEchAn),R18) | S19: =IF(E19>0,E19,IF(D19>0,IF(AND(EchFIXE,R19>0),ROUND((L19-C19)*R19/(1-((1+R19)^-D19)),NbDeci),ROUND(L19/D19,NbDeci)),S18))
H20: =IF(L20=0,"",H19+1) | I20: =IF(L20>0,NbEch+Différé+1-H20,"") | J20: =IF(ISNUMBER(K20),YEAR(K20),"") | K20: =IF(L20=0,"",IF(Ijour=0,MIN(DATE(YEAR(DebAmort),MONTH(DebAmort)+MoisD+(H20-1)*Imois,Jour2),DATE(YEAR(DebAmort),MONTH(DebAmort)+MoisD+1+(H20-1)*Imois,0)),DATE(YEAR(DebAmort),MONTH(DebAmort),Jour1+(H20-1)*Ijour))) | L20: =L19-N19 | M20: =IF(H20<=NoEchMaxi,ROUND(L20*R20,NbDeci),0) | N20: =IF(OR(H20<=Différé,H20>NoEchMaxi),IF(DiffTotal,-M20,0),IF(H20>=NoEchRemb,L20,IF(S20-(M20*EchFIXE)>L20-2,L20,S20-(M20*EchFIXE))))+C20 | O20: =IF(OR(L20=0,H20>NoEchMaxi),0,ROUND(FraisF+FraisV*L20,NbDeci))+F20 | P20: =SUM(M20:O20) | R20: =IF(B20>0,IF(TauxActuariel,((B20+1)^(1/NbEchAn))-1,B20/NbEchAn),R19) | S20: =IF(E20>0,E20,IF(D20>0,IF(AND(EchFIXE,R20>0),ROUND((L20-C20)*R20/(1-((1+R20)^-D20)),NbDeci),ROUND(L20/D20,NbDeci)),S19))
H21: =IF(L21=0,"",H20+1) | I21: =IF(L21>0,NbEch+Différé+1-H21,"") | J21: =IF(ISNUMBER(K21),YEAR(K21),"") | K21: =IF(L21=0,"",IF(Ijour=0,MIN(DATE(YEAR(DebAmort),MONTH(DebAmort)+(H21-1)*Imois,Jour1),DATE(YEAR(DebAmort),MONTH(DebAmort)+1+(H21-1)*Imois,0)),DATE(YEAR(DebAmort),MONTH(DebAmort),Jour1+(H21-1)*Ijour))) | L21: =L20-N20 | M21: =IF(H21<=NoEchMaxi,ROUND(L21*R21,NbDeci),0) | N21: =IF(OR(H21<=Différé,H21>NoEchMaxi),IF(DiffTotal,-M21,0),IF(H21>=NoEchRemb,L21,IF(S21-(M21*EchFIXE)>L21-2,L21,S21-(M21*EchFIXE))))+C21 | O21: =IF(OR(L21=0,H21>NoEchMaxi),0,ROUND(FraisF+FraisV*L21,NbDeci))+F21 | P21: =SUM(M21:O21) | R21: =IF(B21>0,IF(TauxActuariel,((B21+1)^(1/NbEchAn))-1,B21/NbEchAn),R20) | S21: =IF(E21>0,E21,IF(D21>0,IF(AND(EchFIXE,R21>0),ROUND((L21-C21)*R21/(1-((1+R21)^-D21)),NbDeci),ROUND(L21/D21,NbDeci)),S20))
H22: =IF(L22=0,"",H21+1) | I22: =IF(L22>0,NbEch+Différé+1-H22,"") | J22: =IF(ISNUMBER(K22),YEAR(K22),"") | K22: =IF(L22=0,"",IF(Ijour=0,MIN(DATE(YEAR(DebAmort),MONTH(DebAmort)+MoisD+(H22-1)*Imois,Jour2),DATE(YEAR(DebAmort),MONTH(DebAmort)+MoisD+1+(H22-1)*Imois,0)),DATE(YEAR(DebAmort),MONTH(DebAmort),Jour1+(H22-1)*Ijour))) | L22: =L21-N21 | M22: =IF(H22<=NoEchMaxi,ROUND(L22*R22,NbDeci),0) | N22: =IF(OR(H22<=Différé,H22>NoEchMaxi),IF(DiffTotal,-M22,0),IF(H22>=NoEchRemb,L22,IF(S22-(M22*EchFIXE)>L22-2,L22,S22-(M22*EchFIXE))))+C22 | O22: =IF(OR(L22=0,H22>NoEchMaxi),0,ROUND(FraisF+FraisV*L22,NbDeci))+F22 | P22: =SUM(M22:O22) | R22: =IF(B22>0,IF(TauxActuariel,((B22+1)^(1/NbEchAn))-1,B22/NbEchAn),R21) | S22: =IF(E22>0,E22,IF(D22>0,IF(AND(EchFIXE,R22>0),ROUND((L22-C22)*R22/(1-((1+R22)^-D22)),NbDeci),ROUND(L22/D22,NbDeci)),S21))
H23: =IF(L23=0,"",H22+1) | I23: =IF(L23>0,NbEch+Différé+1-H23,"") | J23: =IF(ISNUMBER(K23),YEAR(K23),"") | K23: =IF(L23=0,"",IF(Ijour=0,MIN(DATE(YEAR(DebAmort),MONTH(DebAmort)+(H23-1)*Imois,Jour1),DATE(YEAR(DebAmort),MONTH(DebAmort)+1+(H23-1)*Imois,0)),DATE(YEAR(DebAmort),MONTH(DebAmort),Jour1+(H23-1)*Ijour))) | L23: =L22-N22 | M23: =IF(H23<=NoEchMaxi,ROUND(L23*R23,NbDeci),0) | N23: =IF(OR(H23<=Différé,H23>NoEchMaxi),IF(DiffTotal,-M23,0),IF(H23>=NoEchRemb,L23,IF(S23-(M23*EchFIXE)>L23-2,L23,S23-(M23*EchFIXE))))+C23 | O23: =IF(OR(L23=0,H23>NoEchMaxi),0,ROUND(FraisF+FraisV*L23,NbDeci))+F23 | P23: =SUM(M23:O23) | R23: =IF(B23>0,IF(TauxActuariel,((B23+1)^(1/NbEchAn))-1,B23/NbEchAn),R22) | S23: =IF(E23>0,E23,IF(D23>0,IF(AND(EchFIXE,R23>0),ROUND((L23-C23)*R23/(1-((1+R23)^-D23)),NbDeci),ROUND(L23/D23,NbDeci)),S22))
H24: =IF(L24=0,"",H23+1) | I24: =IF(L24>0,NbEch+Différé+1-H24,"") | J24: =IF(ISNUMBER(K24),YEAR(K24),"") | K24: =IF(L24=0,"",IF(Ijour=0,MIN(DATE(YEAR(DebAmort),MONTH(DebAmort)+MoisD+(H24-1)*Imois,Jour2),DATE(YEAR(DebAmort),MONTH(DebAmort)+MoisD+1+(H24-1)*Imois,0)),DATE(YEAR(DebAmort),MONTH(DebAmort),Jour1+(H24-1)*Ijour))) | L24: =L23-N23 | M24: =IF(H24<=NoEchMaxi,ROUND(L24*R24,NbDeci),0) | N24: =IF(OR(H24<=Différé,H24>NoEchMaxi),IF(DiffTotal,-M24,0),IF(H24>=NoEchRemb,L24,IF(S24-(M24*EchFIXE)>L24-2,L24,S24-(M24*EchFIXE))))+C24 | O24: =IF(OR(L24=0,H24>NoEchMaxi),0,ROUND(FraisF+FraisV*L24,NbDeci))+F24 | P24: =SUM(M24:O24) | R24: =IF(B24>0,IF(TauxActuariel,((B24+1)^(1/NbEchAn))-1,B24/NbEchAn),R23) | S24: =IF(E24>0,E24,IF(D24>0,IF(AND(EchFIXE,R24>0),ROUND((L24-C24)*R24/(1-((1+R24)^-D24)),NbDeci),ROUND(L24/D24,NbDeci)),S23))
H25: =IF(L25=0,"",H24+1) | I25: =IF(L25>0,NbEch+Différé+1-H25,"") | J25: =IF(ISNUMBER(K25),YEAR(K25),"") | K25: =IF(L25=0,"",IF(Ijour=0,MIN(DATE(YEAR(DebAmort),MONTH(DebAmort)+(H25-1)*Imois,Jour1),DATE(YEAR(DebAmort),MONTH(DebAmort)+1+(H25-1)*Imois,0)),DATE(YEAR(DebAmort),MONTH(DebAmort),Jour1+(H25-1)*Ijour))) | L25: =L24-N24 | M25: =IF(H25<=NoEchMaxi,ROUND(L25*R25,NbDeci),0) | N25: =IF(OR(H25<=Différé,H25>NoEchMaxi),IF(DiffTotal,-M25,0),IF(H25>=NoEchRemb,L25,IF(S25-(M25*EchFIXE)>L25-2,L25,S25-(M25*EchFIXE))))+C25 | O25: =IF(OR(L25=0,H25>NoEchMaxi),0,ROUND(FraisF+FraisV*L25,NbDeci))+F25 | P25: =SUM(M25:O25) | R25: =IF(B25>0,IF(TauxActuariel,((B25+1)^(1/NbEchAn))-1,B25/NbEchAn),R24) | S25: =IF(E25>0,E25,IF(D25>0,IF(AND(EchFIXE,R25>0),ROUND((L25-C25)*R25/(1-((1+R25)^-D25)),NbDeci),ROUND(L25/D25,NbDeci)),S24))
H26: =IF(L26=0,"",H25+1) | I26: =IF(L26>0,NbEch+Différé+1-H26,"") | J26: =IF(ISNUMBER(K26),YEAR(K26),"") | K26: =IF(L26=0,"",IF(Ijour=0,MIN(DATE(YEAR(DebAmort),MONTH(DebAmort)+MoisD+(H26-1)*Imois,Jour2),DATE(YEAR(DebAmort),MONTH(DebAmort)+MoisD+1+(H26-1)*Imois,0)),DATE(YEAR(DebAmort),MONTH(DebAmort),Jour1+(H26-1)*Ijour))) | L26: =L25-N25 | M26: =IF(H26<=NoEchMaxi,ROUND(L26*R26,NbDeci),0) | N26: =IF(OR(H26<=Différé,H26>NoEchMaxi),IF(DiffTotal,-M26,0),IF(H26>=NoEchRemb,L26,IF(S26-(M26*EchFIXE)>L26-2,L26,S26-(M26*EchFIXE))))+C26 | O26: =IF(OR(L26=0,H26>NoEchMaxi),0,ROUND(FraisF+FraisV*L26,NbDeci))+F26 | P26: =SUM(M26:O26) | R26: =IF(B26>0,IF(TauxActuariel,((B26+1)^(1/NbEchAn))-1,B26/NbEchAn),R25) | S26: =IF(E26>0,E26,IF(D26>0,IF(AND(EchFIXE,R26>0),ROUND((L26-C26)*R26/(1-((1+R26)^-D26)),NbDeci),ROUND(L26/D26,NbDeci)),S25))
H27: =IF(L27=0,"",H26+1) | I27: =IF(L27>0,NbEch+Différé+1-H27,"") | J27: =IF(ISNUMBER(K27),YEAR(K27),"") | K27: =IF(L27=0,"",IF(Ijour=0,MIN(DATE(YEAR(DebAmort),MONTH(DebAmort)+(H27-1)*Imois,Jour1),DATE(YEAR(DebAmort),MONTH(DebAmort)+1+(H27-1)*Imois,0)),DATE(YEAR(DebAmort),MONTH(DebAmort),Jour1+(H27-1)*Ijour))) | L27: =L26-N26 | M27: =IF(H27<=NoEchMaxi,ROUND(L27*R27,NbDeci),0) | N27: =IF(OR(H27<=Différé,H27>NoEchMaxi),IF(DiffTotal,-M27,0),IF(H27>=NoEchRemb,L27,IF(S27-(M27*EchFIXE)>L27-2,L27,S27-(M27*EchFIXE))))+C27 | O27: =IF(OR(L27=0,H27>NoEchMaxi),0,ROUND(FraisF+FraisV*L27,NbDeci))+F27 | P27: =SUM(M27:O27) | R27: =IF(B27>0,IF(TauxActuariel,((B27+1)^(1/NbEchAn))-1,B27/NbEchAn),R26) | S27: =IF(E27>0,E27,IF(D27>0,IF(AND(EchFIXE,R27>0),ROUND((L27-C27)*R27/(1-((1+R27)^-D27)),NbDeci),ROUND(L27/D27,NbDeci)),S26))
H28: =IF(L28=0,"",H27+1) | I28: =IF(L28>0,NbEch+Différé+1-H28,"") | J28: =IF(ISNUMBER(K28),YEAR(K28),"") | K28: =IF(L28=0,"",IF(Ijour=0,MIN(DATE(YEAR(DebAmort),MONTH(DebAmort)+MoisD+(H28-1)*Imois,Jour2),DATE(YEAR(DebAmort),MONTH(DebAmort)+MoisD+1+(H28-1)*Imois,0)),DATE(YEAR(DebAmort),MONTH(DebAmort),Jour1+(H28-1)*Ijour))) | L28: =L27-N27 | M28: =IF(H28<=NoEchMaxi,ROUND(L28*R28,NbDeci),0) | N28: =IF(OR(H28<=Différé,H28>NoEchMaxi),IF(DiffTotal,-M28,0),IF(H28>=NoEchRemb,L28,IF(S28-(M28*EchFIXE)>L28-2,L28,S28-(M28*EchFIXE))))+C28 | O28: =IF(OR(L28=0,H28>NoEchMaxi),0,ROUND(FraisF+FraisV*L28,NbDeci))+F28 | P28: =SUM(M28:O28) | R28: =IF(B28>0,IF(TauxActuariel,((B28+1)^(1/NbEchAn))-1,B28/NbEchAn),R27) | S28: =IF(E28>0,E28,IF(D28>0,IF(AND(EchFIXE,R28>0),ROUND((L28-C28)*R28/(1-((1+R28)^-D28)),NbDeci),ROUND(L28/D28,NbDeci)),S27))
H29: =IF(L29=0,"",H28+1) | I29: =IF(L29>0,NbEch+Différé+1-H29,"") | J29: =IF(ISNUMBER(K29),YEAR(K29),"") | K29: =IF(L29=0,"",IF(Ijour=0,MIN(DATE(YEAR(DebAmort),MONTH(DebAmort)+(H29-1)*Imois,Jour1),DATE(YEAR(DebAmort),MONTH(DebAmort)+1+(H29-1)*Imois,0)),DATE(YEAR(DebAmort),MONTH(DebAmort),Jour1+(H29-1)*Ijour))) | L29: =L28-N28 | M29: =IF(H29<=NoEchMaxi,ROUND(L29*R29,NbDeci),0) | N29: =IF(OR(H29<=Différé,H29>NoEchMaxi),IF(DiffTotal,-M29,0),IF(H29>=NoEchRemb,L29,IF(S29-(M29*EchFIXE)>L29-2,L29,S29-(M29*EchFIXE))))+C29 | O29: =IF(OR(L29=0,H29>NoEchMaxi),0,ROUND(FraisF+FraisV*L29,NbDeci))+F29 | P29: =SUM(M29:O29) | R29: =IF(B29>0,IF(TauxActuariel,((B29+1)^(1/NbEchAn))-1,B29/NbEchAn),R28) | S29: =IF(E29>0,E29,IF(D29>0,IF(AND(EchFIXE,R29>0),ROUND((L29-C29)*R29/(1-((1+R29)^-D29)),NbDeci),ROUND(L29/D29,NbDeci)),S28))
H30: =IF(L30=0,"",H29+1) | I30: =IF(L30>0,NbEch+Différé+1-H30,"") | J30: =IF(ISNUMBER(K30),YEAR(K30),"") | K30: =IF(L30=0,"",IF(Ijour=0,MIN(DATE(YEAR(DebAmort),MONTH(DebAmort)+MoisD+(H30-1)*Imois,Jour2),DATE(YEAR(DebAmort),MONTH(DebAmort)+MoisD+1+(H30-1)*Imois,0)),DATE(YEAR(DebAmort),MONTH(DebAmort),Jour1+(H30-1)*Ijour))) | L30: =L29-N29 | M30: =IF(H30<=NoEchMaxi,ROUND(L30*R30,NbDeci),0) | N30: =IF(OR(H30<=Différé,H30>NoEchMaxi),IF(DiffTotal,-M30,0),IF(H30>=NoEchRemb,L30,IF(S30-(M30*EchFIXE)>L30-2,L30,S30-(M30*EchFIXE))))+C30 | O30: =IF(OR(L30=0,H30>NoEchMaxi),0,ROUND(FraisF+FraisV*L30,NbDeci))+F30 | P30: =SUM(M30:O30) | R30: =IF(B30>0,IF(TauxActuariel,((B30+1)^(1/NbEchAn))-1,B30/NbEchAn),R29) | S30: =IF(E30>0,E30,IF(D30>0,IF(AND(EchFIXE,R30>0),ROUND((L30-C30)*R30/(1-((1+R30)^-D30)),NbDeci),ROUND(L30/D30,NbDeci)),S29))
H31: =IF(L31=0,"",H30+1) | I31: =IF(L31>0,NbEch+Différé+1-H31,"") | J31: =IF(ISNUMBER(K31),YEAR(K31),"") | K31: =IF(L31=0,"",IF(Ijour=0,MIN(DATE(YEAR(DebAmort),MONTH(DebAmort)+(H31-1)*Imois,Jour1),DATE(YEAR(DebAmort),MONTH(DebAmort)+1+(H31-1)*Imois,0)),DATE(YEAR(DebAmort),MONTH(DebAmort),Jour1+(H31-1)*Ijour))) | L31: =L30-N30 | M31: =IF(H31<=NoEchMaxi,ROUND(L31*R31,NbDeci),0) | N31: =IF(OR(H31<=Différé,H31>NoEchMaxi),IF(DiffTotal,-M31,0),IF(H31>=NoEchRemb,L31,IF(S31-(M31*EchFIXE)>L31-2,L31,S31-(M31*EchFIXE))))+C31 | O31: =IF(OR(L31=0,H31>NoEchMaxi),0,ROUND(FraisF+FraisV*L31,NbDeci))+F31 | P31: =SUM(M31:O31) | R31: =IF(B31>0,IF(TauxActuariel,((B31+1)^(1/NbEchAn))-1,B31/NbEchAn),R30) | S31: =IF(E31>0,E31,IF(D31>0,IF(AND(EchFIXE,R31>0),ROUND((L31-C31)*R31/(1-((1+R31)^-D31)),NbDeci),ROUND(L31/D31,NbDeci)),S30))
H32: =IF(L32=0,"",H31+1) | I32: =IF(L32>0,NbEch+Différé+1-H32,"") | J32: =IF(ISNUMBER(K32),YEAR(K32),"") | K32: =IF(L32=0,"",IF(Ijour=0,MIN(DATE(YEAR(DebAmort),MONTH(DebAmort)+MoisD+(H32-1)*Imois,Jour2),DATE(YEAR(DebAmort),MONTH(DebAmort)+MoisD+1+(H32-1)*Imois,0)),DATE(YEAR(DebAmort),MONTH(DebAmort),Jour1+(H32-1)*Ijour))) | L32: =L31-N31 | M32: =IF(H32<=NoEchMaxi,ROUND(L32*R32,NbDeci),0) | N32: =IF(OR(H32<=Différé,H32>NoEchMaxi),IF(DiffTotal,-M32,0),IF(H32>=NoEchRemb,L32,IF(S32-(M32*EchFIXE)>L32-2,L32,S32-(M32*EchFIXE))))+C32 | O32: =IF(OR(L32=0,H32>NoEchMaxi),0,ROUND(FraisF+FraisV*L32,NbDeci))+F32 | P32: =SUM(M32:O32) | R32: =IF(B32>0,IF(TauxActuariel,((B32+1)^(1/NbEchAn))-1,B32/NbEchAn),R31) | S32: =IF(E32>0,E32,IF(D32>0,IF(AND(EchFIXE,R32>0),ROUND((L32-C32)*R32/(1-((1+R32)^-D32)),NbDeci),ROUND(L32/D32,NbDeci)),S31))
H33: =IF(L33=0,"",H32+1) | I33: =IF(L33>0,NbEch+Différé+1-H33,"") | J33: =IF(ISNUMBER(K33),YEAR(K33),"") | K33: =IF(L33=0,"",IF(Ijour=0,MIN(DATE(YEAR(DebAmort),MONTH(DebAmort)+(H33-1)*Imois,Jour1),DATE(YEAR(DebAmort),MONTH(DebAmort)+1+(H33-1)*Imois,0)),DATE(YEAR(DebAmort),MONTH(DebAmort),Jour1+(H33-1)*Ijour))) | L33: =L32-N32 | M33: =IF(H33<=NoEchMaxi,ROUND(L33*R33,NbDeci),0) | N33: =IF(OR(H33<=Différé,H33>NoEchMaxi),IF(DiffTotal,-M33,0),IF(H33>=NoEchRemb,L33,IF(S33-(M33*EchFIXE)>L33-2,L33,S33-(M33*EchFIXE))))+C33 | O33: =IF(OR(L33=0,H33>NoEchMaxi),0,ROUND(FraisF+FraisV*L33,NbDeci))+F33 | P33: =SUM(M33:O33) | R33: =IF(B33>0,IF(TauxActuariel,((B33+1)^(1/NbEchAn))-1,B33/NbEchAn),R32) | S33: =IF(E33>0,E33,IF(D33>0,IF(AND(EchFIXE,R33>0),ROUND((L33-C33)*R33/(1-((1+R33)^-D33)),NbDeci),ROUND(L33/D33,NbDeci)),S32))
H34: =IF(L34=0,"",H33+1) | I34: =IF(L34>0,NbEch+Différé+1-H34,"") | J34: =IF(ISNUMBER(K34),YEAR(K34),"") | K34: =IF(L34=0,"",IF(Ijour=0,MIN(DATE(YEAR(DebAmort),MONTH(DebAmort)+MoisD+(H34-1)*Imois,Jour2),DATE(YEAR(DebAmort),MONTH(DebAmort)+MoisD+1+(H34-1)*Imois,0)),DATE(YEAR(DebAmort),MONTH(DebAmort),Jour1+(H34-1)*Ijour))) | L34: =L33-N33 | M34: =IF(H34<=NoEchMaxi,ROUND(L34*R34,NbDeci),0) | N34: =IF(OR(H34<=Différé,H34>NoEchMaxi),IF(DiffTotal,-M34,0),IF(H34>=NoEchRemb,L34,IF(S34-(M34*EchFIXE)>L34-2,L34,S34-(M34*EchFIXE))))+C34 | O34: =IF(OR(L34=0,H34>NoEchMaxi),0,ROUND(FraisF+FraisV*L34,NbDeci))+F34 | P34: =SUM(M34:O34) | R34: =IF(B34>0,IF(TauxActuariel,((B34+1)^(1/NbEchAn))-1,B34/NbEchAn),R33) | S34: =IF(E34>0,E34,IF(D34>0,IF(AND(EchFIXE,R34>0),ROUND((L34-C34)*R34/(1-((1+R34)^-D34)),NbDeci),ROUND(L34/D34,NbDeci)),S33))
H35: =IF(L35=0,"",H34+1) | I35: =IF(L35>0,NbEch+Différé+1-H35,"") | J35: =IF(ISNUMBER(K35),YEAR(K35),"") | K35: =IF(L35=0,"",IF(Ijour=0,MIN(DATE(YEAR(DebAmort),MONTH(DebAmort)+(H35-1)*Imois,Jour1),DATE(YEAR(DebAmort),MONTH(DebAmort)+1+(H35-1)*Imois,0)),DATE(YEAR(DebAmort),MONTH(DebAmort),Jour1+(H35-1)*Ijour))) | L35: =L34-N34 | M35: =IF(H35<=NoEchMaxi,ROUND(L35*R35,NbDeci),0) | N35: =IF(OR(H35<=Différé,H35>NoEchMaxi),IF(DiffTotal,-M35,0),IF(H35>=NoEchRemb,L35,IF(S35-(M35*EchFIXE)>L35-2,L35,S35-(M35*EchFIXE))))+C35 | O35: =IF(OR(L35=0,H35>NoEchMaxi),0,ROUND(FraisF+FraisV*L35,NbDeci))+F35 | P35: =SUM(M35:O35) | R35: =IF(B35>0,IF(TauxActuariel,((B35+1)^(1/NbEchAn))-1,B35/NbEchAn),R34) | S35: =IF(E35>0,E35,IF(D35>0,IF(AND(EchFIXE,R35>0),ROUND((L35-C35)*R35/(1-((1+R35)^-D35)),NbDeci),ROUND(L35/D35,NbDeci)),S34))
H36: =IF(L36=0,"",H35+1) | I36: =IF(L36>0,NbEch+Différé+1-H36,"") | J36: =IF(ISNUMBER(K36),YEAR(K36),"") | K36: =IF(L36=0,"",IF(Ijour=0,MIN(DATE(YEAR(DebAmort),MONTH(DebAmort)+MoisD+(H36-1)*Imois,Jour2),DATE(YEAR(DebAmort),MONTH(DebAmort)+MoisD+1+(H36-1)*Imois,0)),DATE(YEAR(DebAmort),MONTH(DebAmort),Jour1+(H36-1)*Ijour))) | L36: =L35-N35 | M36: =IF(H36<=NoEchMaxi,ROUND(L36*R36,NbDeci),0) | N36: =IF(OR(H36<=Différé,H36>NoEchMaxi),IF(DiffTotal,-M36,0),IF(H36>=NoEchRemb,L36,IF(S36-(M36*EchFIXE)>L36-2,L36,S36-(M36*EchFIXE))))+C36 | O36: =IF(OR(L36=0,H36>NoEchMaxi),0,ROUND(FraisF+FraisV*L36,NbDeci))+F36 | P36: =SUM(M36:O36) | R36: =IF(B36>0,IF(TauxActuariel,((B36+1)^(1/NbEchAn))-1,B36/NbEchAn),R35) | S36: =IF(E36>0,E36,IF(D36>0,IF(AND(EchFIXE,R36>0),ROUND((L36-C36)*R36/(1-((1+R36)^-D36)),NbDeci),ROUND(L36/D36,NbDeci)),S35))
H37: =IF(L37=0,"",H36+1) | I37: =IF(L37>0,NbEch+Différé+1-H37,"") | J37: =IF(ISNUMBER(K37),YEAR(K37),"") | K37: =IF(L37=0,"",IF(Ijour=0,MIN(DATE(YEAR(DebAmort),MONTH(DebAmort)+(H37-1)*Imois,Jour1),DATE(YEAR(DebAmort),MONTH(DebAmort)+1+(H37-1)*Imois,0)),DATE(YEAR(DebAmort),MONTH(DebAmort),Jour1+(H37-1)*Ijour))) | L37: =L36-N36 | M37: =IF(H37<=NoEchMaxi,ROUND(L37*R37,NbDeci),0) | N37: =IF(OR(H37<=Différé,H37>NoEchMaxi),IF(DiffTotal,-M37,0),IF(H37>=NoEchRemb,L37,IF(S37-(M37*EchFIXE)>L37-2,L37,S37-(M37*EchFIXE))))+C37 | O37: =IF(OR(L37=0,H37>NoEchMaxi),0,ROUND(FraisF+FraisV*L37,NbDeci))+F37 | P37: =SUM(M37:O37) | R37: =IF(B37>0,IF(TauxActuariel,((B37+1)^(1/NbEchAn))-1,B37/NbEchAn),R36) | S37: =IF(E37>0,E37,IF(D37>0,IF(AND(EchFIXE,R37>0),ROUND((L37-C37)*R37/(1-((1+R37)^-D37)),NbDeci),ROUND(L37/D37,NbDeci)),S36))
H38: =IF(L38=0,"",H37+1) | I38: =IF(L38>0,NbEch+Différé+1-H38,"") | J38: =IF(ISNUMBER(K38),YEAR(K38),"") | K38: =IF(L38=0,"",IF(Ijour=0,MIN(DATE(YEAR(DebAmort),MONTH(DebAmort)+MoisD+(H38-1)*Imois,Jour2),DATE(YEAR(DebAmort),MONTH(DebAmort)+MoisD+1+(H38-1)*Imois,0)),DATE(YEAR(DebAmort),MONTH(DebAmort),Jour1+(H38-1)*Ijour))) | L38: =L37-N37 | M38: =IF(H38<=NoEchMaxi,ROUND(L38*R38,NbDeci),0) | N38: =IF(OR(H38<=Différé,H38>NoEchMaxi),IF(DiffTotal,-M38,0),IF(H38>=NoEchRemb,L38,IF(S38-(M38*EchFIXE)>L38-2,L38,S38-(M38*EchFIXE))))+C38 | O38: =IF(OR(L38=0,H38>NoEchMaxi),0,ROUND(FraisF+FraisV*L38,NbDeci))+F38 | P38: =SUM(M38:O38) | R38: =IF(B38>0,IF(TauxActuariel,((B38+1)^(1/NbEchAn))-1,B38/NbEchAn),R37) | S38: =IF(E38>0,E38,IF(D38>0,IF(AND(EchFIXE,R38>0),ROUND((L38-C38)*R38/(1-((1+R38)^-D38)),NbDeci),ROUND(L38/D38,NbDeci)),S37))
H39: =IF(L39=0,"",H38+1) | I39: =IF(L39>0,NbEch+Différé+1-H39,"") | J39: =IF(ISNUMBER(K39),YEAR(K39),"") | K39: =IF(L39=0,"",IF(Ijour=0,MIN(DATE(YEAR(DebAmort),MONTH(DebAmort)+(H39-1)*Imois,Jour1),DATE(YEAR(DebAmort),MONTH(DebAmort)+1+(H39-1)*Imois,0)),DATE(YEAR(DebAmort),MONTH(DebAmort),Jour1+(H39-1)*Ijour))) | L39: =L38-N38 | M39: =IF(H39<=NoEchMaxi,ROUND(L39*R39,NbDeci),0) | N39: =IF(OR(H39<=Différé,H39>NoEchMaxi),IF(DiffTotal,-M39,0),IF(H39>=NoEchRemb,L39,IF(S39-(M39*EchFIXE)>L39-2,L39,S39-(M39*EchFIXE))))+C39 | O39: =IF(OR(L39=0,H39>NoEchMaxi),0,ROUND(FraisF+FraisV*L39,NbDeci))+F39 | P39: =SUM(M39:O39) | R39: =IF(B39>0,IF(TauxActuariel,((B39+1)^(1/NbEchAn))-1,B39/NbEchAn),R38) | S39: =IF(E39>0,E39,IF(D39>0,IF(AND(EchFIXE,R39>0),ROUND((L39-C39)*R39/(1-((1+R39)^-D39)),NbDeci),ROUND(L39/D39,NbDeci)),S38))
H40: =IF(L40=0,"",H39+1) | I40: =IF(L40>0,NbEch+Différé+1-H40,"") | J40: =IF(ISNUMBER(K40),YEAR(K40),"") | K40: =IF(L40=0,"",IF(Ijour=0,MIN(DATE(YEAR(DebAmort),MONTH(DebAmort)+MoisD+(H40-1)*Imois,Jour2),DATE(YEAR(DebAmort),MONTH(DebAmort)+MoisD+1+(H40-1)*Imois,0)),DATE(YEAR(DebAmort),MONTH(DebAmort),Jour1+(H40-1)*Ijour))) | L40: =L39-N39 | M40: =IF(H40<=NoEchMaxi,ROUND(L40*R40,NbDeci),0) | N40: =IF(OR(H40<=Différé,H40>NoEchMaxi),IF(DiffTotal,-M40,0),IF(H40>=NoEchRemb,L40,IF(S40-(M40*EchFIXE)>L40-2,L40,S40-(M40*EchFIXE))))+C40 | O40: =IF(OR(L40=0,H40>NoEchMaxi),0,ROUND(FraisF+FraisV*L40,NbDeci))+F40 | P40: =SUM(M40:O40) | R40: =IF(B40>0,IF(TauxActuariel,((B40+1)^(1/NbEchAn))-1,B40/NbEchAn),R39) | S40: =IF(E40>0,E40,IF(D40>0,IF(AND(EchFIXE,R40>0),ROUND((L40-C40)*R40/(1-((1+R40)^-D40)),NbDeci),ROUND(L40/D40,NbDeci)),S39))
H41: =IF(L41=0,"",H40+1) | I41: =IF(L41>0,NbEch+Différé+1-H41,"") | J41: =IF(ISNUMBER(K41),YEAR(K41),"") | K41: =IF(L41=0,"",IF(Ijour=0,MIN(DATE(YEAR(DebAmort),MONTH(DebAmort)+(H41-1)*Imois,Jour1),DATE(YEAR(DebAmort),MONTH(DebAmort)+1+(H41-1)*Imois,0)),DATE(YEAR(DebAmort),MONTH(DebAmort),Jour1+(H41-1)*Ijour))) | L41: =L40-N40 | M41: =IF(H41<=NoEchMaxi,ROUND(L41*R41,NbDeci),0) | N41: =IF(OR(H41<=Différé,H41>NoEchMaxi),IF(DiffTotal,-M41,0),IF(H41>=NoEchRemb,L41,IF(S41-(M41*EchFIXE)>L41-2,L41,S41-(M41*EchFIXE))))+C41 | O41: =IF(OR(L41=0,H41>NoEchMaxi),0,ROUND(FraisF+FraisV*L41,NbDeci))+F41 | P41: =SUM(M41:O41) | R41: =IF(B41>0,IF(TauxActuariel,((B41+1)^(1/NbEchAn))-1,B41/NbEchAn),R40) | S41: =IF(E41>0,E41,IF(D41>0,IF(AND(EchFIXE,R41>0),ROUND((L41-C41)*R41/(1-((1+R41)^-D41)),NbDeci),ROUND(L41/D41,NbDeci)),S40))
H42: =IF(L42=0,"",H41+1) | I42: =IF(L42>0,NbEch+Différé+1-H42,"") | J42: =IF(ISNUMBER(K42),YEAR(K42),"") | K42: =IF(L42=0,"",IF(Ijour=0,MIN(DATE(YEAR(DebAmort),MONTH(DebAmort)+MoisD+(H42-1)*Imois,Jour2),DATE(YEAR(DebAmort),MONTH(DebAmort)+MoisD+1+(H42-1)*Imois,0)),DATE(YEAR(DebAmort),MONTH(DebAmort),Jour1+(H42-1)*Ijour))) | L42: =L41-N41 | M42: =IF(H42<=NoEchMaxi,ROUND(L42*R42,NbDeci),0) | N42: =IF(OR(H42<=Différé,H42>NoEchMaxi),IF(DiffTotal,-M42,0),IF(H42>=NoEchRemb,L42,IF(S42-(M42*EchFIXE)>L42-2,L42,S42-(M42*EchFIXE))))+C42 | O42: =IF(OR(L42=0,H42>NoEchMaxi),0,ROUND(FraisF+FraisV*L42,NbDeci))+F42 | P42: =SUM(M42:O42) | R42: =IF(B42>0,IF(TauxActuariel,((B42+1)^(1/NbEchAn))-1,B42/NbEchAn),R41) | S42: =IF(E42>0,E42,IF(D42>0,IF(AND(EchFIXE,R42>0),ROUND((L42-C42)*R42/(1-((1+R42)^-D42)),NbDeci),ROUND(L42/D42,NbDeci)),S41))
H43: =IF(L43=0,"",H42+1) | I43: =IF(L43>0,NbEch+Différé+1-H43,"") | J43: =IF(ISNUMBER(K43),YEAR(K43),"") | K43: =IF(L43=0,"",IF(Ijour=0,MIN(DATE(YEAR(DebAmort),MONTH(DebAmort)+(H43-1)*Imois,Jour1),DATE(YEAR(DebAmort),MONTH(DebAmort)+1+(H43-1)*Imois,0)),DATE(YEAR(DebAmort),MONTH(DebAmort),Jour1+(H43-1)*Ijour))) | L43: =L42-N42 | M43: =IF(H43<=NoEchMaxi,ROUND(L43*R43,NbDeci),0) | N43: =IF(OR(H43<=Différé,H43>NoEchMaxi),IF(DiffTotal,-M43,0),IF(H43>=NoEchRemb,L43,IF(S43-(M43*EchFIXE)>L43-2,L43,S43-(M43*EchFIXE))))+C43 | O43: =IF(OR(L43=0,H43>NoEchMaxi),0,ROUND(FraisF+FraisV*L43,NbDeci))+F43 | P43: =SUM(M43:O43) | R43: =IF(B43>0,IF(TauxActuariel,((B43+1)^(1/NbEchAn))-1,B43/NbEchAn),R42) | S43: =IF(E43>0,E43,IF(D43>0,IF(AND(EchFIXE,R43>0),ROUND((L43-C43)*R43/(1-((1+R43)^-D43)),NbDeci),ROUND(L43/D43,NbDeci)),S42))
H44: =IF(L44=0,"",H43+1) | I44: =IF(L44>0,NbEch+Différé+1-H44,"") | J44: =IF(ISNUMBER(K44),YEAR(K44),"") | K44: =IF(L44=0,"",IF(Ijour=0,MIN(DATE(YEAR(DebAmort),MONTH(DebAmort)+MoisD+(H44-1)*Imois,Jour2),DATE(YEAR(DebAmort),MONTH(DebAmort)+MoisD+1+(H44-1)*Imois,0)),DATE(YEAR(DebAmort),MONTH(DebAmort),Jour1+(H44-1)*Ijour))) | L44: =L43-N43 | M44: =IF(H44<=NoEchMaxi,ROUND(L44*R44,NbDeci),0) | N44: =IF(OR(H44<=Différé,H44>NoEchMaxi),IF(DiffTotal,-M44,0),IF(H44>=NoEchRemb,L44,IF(S44-(M44*EchFIXE)>L44-2,L44,S44-(M44*EchFIXE))))+C44 | O44: =IF(OR(L44=0,H44>NoEchMaxi),0,ROUND(FraisF+FraisV*L44,NbDeci))+F44 | P44: =SUM(M44:O44) | R44: =IF(B44>0,IF(TauxActuariel,((B44+1)^(1/NbEchAn))-1,B44/NbEchAn),R43) | S44: =IF(E44>0,E44,IF(D44>0,IF(AND(EchFIXE,R44>0),ROUND((L44-C44)*R44/(1-((1+R44)^-D44)),NbDeci),ROUND(L44/D44,NbDeci)),S43))
H45: =IF(L45=0,"",H44+1) | I45: =IF(L45>0,NbEch+Différé+1-H45,"") | J45: =IF(ISNUMBER(K45),YEAR(K45),"") | K45: =IF(L45=0,"",IF(Ijour=0,MIN(DATE(YEAR(DebAmort),MONTH(DebAmort)+(H45-1)*Imois,Jour1),DATE(YEAR(DebAmort),MONTH(DebAmort)+1+(H45-1)*Imois,0)),DATE(YEAR(DebAmort),MONTH(DebAmort),Jour1+(H45-1)*Ijour))) | L45: =L44-N44 | M45: =IF(H45<=NoEchMaxi,ROUND(L45*R45,NbDeci),0) | N45: =IF(OR(H45<=Différé,H45>NoEchMaxi),IF(DiffTotal,-M45,0),IF(H45>=NoEchRemb,L45,IF(S45-(M45*EchFIXE)>L45-2,L45,S45-(M45*EchFIXE))))+C45 | O45: =IF(OR(L45=0,H45>NoEchMaxi),0,ROUND(FraisF+FraisV*L45,NbDeci))+F45 | P45: =SUM(M45:O45) | R45: =IF(B45>0,IF(TauxActuariel,((B45+1)^(1/NbEchAn))-1,B45/NbEchAn),R44) | S45: =IF(E45>0,E45,IF(D45>0,IF(AND(EchFIXE,R45>0),ROUND((L45-C45)*R45/(1-((1+R45)^-D45)),NbDeci),ROUND(L45/D45,NbDeci)),S44))
H46: =IF(L46=0,"",H45+1) | I46: =IF(L46>0,NbEch+Différé+1-H46,"") | J46: =IF(ISNUMBER(K46),YEAR(K46),"") | K46: =IF(L46=0,"",IF(Ijour=0,MIN(DATE(YEAR(DebAmort),MONTH(DebAmort)+MoisD+(H46-1)*Imois,Jour2),DATE(YEAR(DebAmort),MONTH(DebAmort)+MoisD+1+(H46-1)*Imois,0)),DATE(YEAR(DebAmort),MONTH(DebAmort),Jour1+(H46-1)*Ijour))) | L46: =L45-N45 | M46: =IF(H46<=NoEchMaxi,ROUND(L46*R46,NbDeci),0) | N46: =IF(OR(H46<=Différé,H46>NoEchMaxi),IF(DiffTotal,-M46,0),IF(H46>=NoEchRemb,L46,IF(S46-(M46*EchFIXE)>L46-2,L46,S46-(M46*EchFIXE))))+C46 | O46: =IF(OR(L46=0,H46>NoEchMaxi),0,ROUND(FraisF+FraisV*L46,NbDeci))+F46 | P46: =SUM(M46:O46) | R46: =IF(B46>0,IF(TauxActuariel,((B46+1)^(1/NbEchAn))-1,B46/NbEchAn),R45) | S46: =IF(E46>0,E46,IF(D46>0,IF(AND(EchFIXE,R46>0),ROUND((L46-C46)*R46/(1-((1+R46)^-D46)),NbDeci),ROUND(L46/D46,NbDeci)),S45))
H47: =IF(L47=0,"",H46+1) | I47: =IF(L47>0,NbEch+Différé+1-H47,"") | J47: =IF(ISNUMBER(K47),YEAR(K47),"") | K47: =IF(L47=0,"",IF(Ijour=0,MIN(DATE(YEAR(DebAmort),MONTH(DebAmort)+(H47-1)*Imois,Jour1),DATE(YEAR(DebAmort),MONTH(DebAmort)+1+(H47-1)*Imois,0)),DATE(YEAR(DebAmort),MONTH(DebAmort),Jour1+(H47-1)*Ijour))) | L47: =L46-N46 | M47: =IF(H47<=NoEchMaxi,ROUND(L47*R47,NbDeci),0) | N47: =IF(OR(H47<=Différé,H47>NoEchMaxi),IF(DiffTotal,-M47,0),IF(H47>=NoEchRemb,L47,IF(S47-(M47*EchFIXE)>L47-2,L47,S47-(M47*EchFIXE))))+C47 | O47: =IF(OR(L47=0,H47>NoEchMaxi),0,ROUND(FraisF+FraisV*L47,NbDeci))+F47 | P47: =SUM(M47:O47) | R47: =IF(B47>0,IF(TauxActuariel,((B47+1)^(1/NbEchAn))-1,B47/NbEchAn),R46) | S47: =IF(E47>0,E47,IF(D47>0,IF(AND(EchFIXE,R47>0),ROUND((L47-C47)*R47/(1-((1+R47)^-D47)),NbDeci),ROUND(L47/D47,NbDeci)),S46))
H48: =IF(L48=0,"",H47+1) | I48: =IF(L48>0,NbEch+Différé+1-H48,"") | J48: =IF(ISNUMBER(K48),YEAR(K48),"") | K48: =IF(L48=0,"",IF(Ijour=0,MIN(DATE(YEAR(DebAmort),MONTH(DebAmort)+MoisD+(H48-1)*Imois,Jour2),DATE(YEAR(DebAmort),MONTH(DebAmort)+MoisD+1+(H48-1)*Imois,0)),DATE(YEAR(DebAmort),MONTH(DebAmort),Jour1+(H48-1)*Ijour))) | L48: =L47-N47 | M48: =IF(H48<=NoEchMaxi,ROUND(L48*R48,NbDeci),0) | N48: =IF(OR(H48<=Différé,H48>NoEchMaxi),IF(DiffTotal,-M48,0),IF(H48>=NoEchRemb,L48,IF(S48-(M48*EchFIXE)>L48-2,L48,S48-(M48*EchFIXE))))+C48 | O48: =IF(OR(L48=0,H48>NoEchMaxi),0,ROUND(FraisF+FraisV*L48,NbDeci))+F48 | P48: =SUM(M48:O48) | R48: =IF(B48>0,IF(TauxActuariel,((B48+1)^(1/NbEchAn))-1,B48/NbEchAn),R47) | S48: =IF(E48>0,E48,IF(D48>0,IF(AND(EchFIXE,R48>0),ROUND((L48-C48)*R48/(1-((1+R48)^-D48)),NbDeci),ROUND(L48/D48,NbDeci)),S47))
H49: =IF(L49=0,"",H48+1) | I49: =IF(L49>0,NbEch+Différé+1-H49,"") | J49: =IF(ISNUMBER(K49),YEAR(K49),"") | K49: =IF(L49=0,"",IF(Ijour=0,MIN(DATE(YEAR(DebAmort),MONTH(DebAmort)+(H49-1)*Imois,Jour1),DATE(YEAR(DebAmort),MONTH(DebAmort)+1+(H49-1)*Imois,0)),DATE(YEAR(DebAmort),MONTH(DebAmort),Jour1+(H49-1)*Ijour))) | L49: =L48-N48 | M49: =IF(H49<=NoEchMaxi,ROUND(L49*R49,NbDeci),0) | N49: =IF(OR(H49<=Différé,H49>NoEchMaxi),IF(DiffTotal,-M49,0),IF(H49>=NoEchRemb,L49,IF(S49-(M49*EchFIXE)>L49-2,L49,S49-(M49*EchFIXE))))+C49 | O49: =IF(OR(L49=0,H49>NoEchMaxi),0,ROUND(FraisF+FraisV*L49,NbDeci))+F49 | P49: =SUM(M49:O49) | R49: =IF(B49>0,IF(TauxActuariel,((B49+1)^(1/NbEchAn))-1,B49/NbEchAn),R48) | S49: =IF(E49>0,E49,IF(D49>0,IF(AND(EchFIXE,R49>0),ROUND((L49-C49)*R49/(1-((1+R49)^-D49)),NbDeci),ROUND(L49/D49,NbDeci)),S48))
H50: =IF(L50=0,"",H49+1) | I50: =IF(L50>0,NbEch+Différé+1-H50,"") | J50: =IF(ISNUMBER(K50),YEAR(K50),"") | K50: =IF(L50=0,"",IF(Ijour=0,MIN(DATE(YEAR(DebAmort),MONTH(DebAmort)+MoisD+(H50-1)*Imois,Jour2),DATE(YEAR(DebAmort),MONTH(DebAmort)+MoisD+1+(H50-1)*Imois,0)),DATE(YEAR(DebAmort),MONTH(DebAmort),Jour1+(H50-1)*Ijour))) | L50: =L49-N49 | M50: =IF(H50<=NoEchMaxi,ROUND(L50*R50,NbDeci),0) | N50: =IF(OR(H50<=Différé,H50>NoEchMaxi),IF(DiffTotal,-M50,0),IF(H50>=NoEchRemb,L50,IF(S50-(M50*EchFIXE)>L50-2,L50,S50-(M50*EchFIXE))))+C50 | O50: =IF(OR(L50=0,H50>NoEchMaxi),0,ROUND(FraisF+FraisV*L50,NbDeci))+F50 | P50: =SUM(M50:O50) | R50: =IF(B50>0,IF(TauxActuariel,((B50+1)^(1/NbEchAn))-1,B50/NbEchAn),R49) | S50: =IF(E50>0,E50,IF(D50>0,IF(AND(EchFIXE,R50>0),ROUND((L50-C50)*R50/(1-((1+R50)^-D50)),NbDeci),ROUND(L50/D50,NbDeci)),S49))
H51: =IF(L51=0,"",H50+1) | I51: =IF(L51>0,NbEch+Différé+1-H51,"") | J51: =IF(ISNUMBER(K51),YEAR(K51),"") | K51: =IF(L51=0,"",IF(Ijour=0,MIN(DATE(YEAR(DebAmort),MONTH(DebAmort)+(H51-1)*Imois,Jour1),DATE(YEAR(DebAmort),MONTH(DebAmort)+1+(H51-1)*Imois,0)),DATE(YEAR(DebAmort),MONTH(DebAmort),Jour1+(H51-1)*Ijour))) | L51: =L50-N50 | M51: =IF(H51<=NoEchMaxi,ROUND(L51*R51,NbDeci),0) | N51: =IF(OR(H51<=Différé,H51>NoEchMaxi),IF(DiffTotal,-M51,0),IF(H51>=NoEchRemb,L51,IF(S51-(M51*EchFIXE)>L51-2,L51,S51-(M51*EchFIXE))))+C51 | O51: =IF(OR(L51=0,H51>NoEchMaxi),0,ROUND(FraisF+FraisV*L51,NbDeci))+F51 | P51: =SUM(M51:O51) | R51: =IF(B51>0,IF(TauxActuariel,((B51+1)^(1/NbEchAn))-1,B51/NbEchAn),R50) | S51: =IF(E51>0,E51,IF(D51>0,IF(AND(EchFIXE,R51>0),ROUND((L51-C51)*R51/(1-((1+R51)^-D51)),NbDeci),ROUND(L51/D51,NbDeci)),S50))
H52: =IF(L52=0,"",H51+1) | I52: =IF(L52>0,NbEch+Différé+1-H52,"") | J52: =IF(ISNUMBER(K52),YEAR(K52),"") | K52: =IF(L52=0,"",IF(Ijour=0,MIN(DATE(YEAR(DebAmort),MONTH(DebAmort)+MoisD+(H52-1)*Imois,Jour2),DATE(YEAR(DebAmort),MONTH(DebAmort)+MoisD+1+(H52-1)*Imois,0)),DATE(YEAR(DebAmort),MONTH(DebAmort),Jour1+(H52-1)*Ijour))) | L52: =L51-N51 | M52: =IF(H52<=NoEchMaxi,ROUND(L52*R52,NbDeci),0) | N52: =IF(OR(H52<=Différé,H52>NoEchMaxi),IF(DiffTotal,-M52,0),IF(H52>=NoEchRemb,L52,IF(S52-(M52*EchFIXE)>L52-2,L52,S52-(M52*EchFIXE))))+C52 | O52: =IF(OR(L52=0,H52>NoEchMaxi),0,ROUND(FraisF+FraisV*L52,NbDeci))+F52 | P52: =SUM(M52:O52) | R52: =IF(B52>0,IF(TauxActuariel,((B52+1)^(1/NbEchAn))-1,B52/NbEchAn),R51) | S52: =IF(E52>0,E52,IF(D52>0,IF(AND(EchFIXE,R52>0),ROUND((L52-C52)*R52/(1-((1+R52)^-D52)),NbDeci),ROUND(L52/D52,NbDeci)),S51))
H53: =IF(L53=0,"",H52+1) | I53: =IF(L53>0,NbEch+Différé+1-H53,"") | J53: =IF(ISNUMBER(K53),YEAR(K53),"") | K53: =IF(L53=0,"",IF(Ijour=0,MIN(DATE(YEAR(DebAmort),MONTH(DebAmort)+(H53-1)*Imois,Jour1),DATE(YEAR(DebAmort),MONTH(DebAmort)+1+(H53-1)*Imois,0)),DATE(YEAR(DebAmort),MONTH(DebAmort),Jour1+(H53-1)*Ijour))) | L53: =L52-N52 | M53: =IF(H53<=NoEchMaxi,ROUND(L53*R53,NbDeci),0) | N53: =IF(OR(H53<=Différé,H53>NoEchMaxi),IF(DiffTotal,-M53,0),IF(H53>=NoEchRemb,L53,IF(S53-(M53*EchFIXE)>L53-2,L53,S53-(M53*EchFIXE))))+C53 | O53: =IF(OR(L53=0,H53>NoEchMaxi),0,ROUND(FraisF+FraisV*L53,NbDeci))+F53 | P53: =SUM(M53:O53) | R53: =IF(B53>0,IF(TauxActuariel,((B53+1)^(1/NbEchAn))-1,B53/NbEchAn),R52) | S53: =IF(E53>0,E53,IF(D53>0,IF(AND(EchFIXE,R53>0),ROUND((L53-C53)*R53/(1-((1+R53)^-D53)),NbDeci),ROUND(L53/D53,NbDeci)),S52))
H54: =IF(L54=0,"",H53+1) | I54: =IF(L54>0,NbEch+Différé+1-H54,"") | J54: =IF(ISNUMBER(K54),YEAR(K54),"") | K54: =IF(L54=0,"",IF(Ijour=0,MIN(DATE(YEAR(DebAmort),MONTH(DebAmort)+MoisD+(H54-1)*Imois,Jour2),DATE(YEAR(DebAmort),MONTH(DebAmort)+MoisD+1+(H54-1)*Imois,0)),DATE(YEAR(DebAmort),MONTH(DebAmort),Jour1+(H54-1)*Ijour))) | L54: =L53-N53 | M54: =IF(H54<=NoEchMaxi,ROUND(L54*R54,NbDeci),0) | N54: =IF(OR(H54<=Différé,H54>NoEchMaxi),IF(DiffTotal,-M54,0),IF(H54>=NoEchRemb,L54,IF(S54-(M54*EchFIXE)>L54-2,L54,S54-(M54*EchFIXE))))+C54 | O54: =IF(OR(L54=0,H54>NoEchMaxi),0,ROUND(FraisF+FraisV*L54,NbDeci))+F54 | P54: =SUM(M54:O54) | R54: =IF(B54>0,IF(TauxActuariel,((B54+1)^(1/NbEchAn))-1,B54/NbEchAn),R53) | S54: =IF(E54>0,E54,IF(D54>0,IF(AND(EchFIXE,R54>0),ROUND((L54-C54)*R54/(1-((1+R54)^-D54)),NbDeci),ROUND(L54/D54,NbDeci)),S53))
H55: =IF(L55=0,"",H54+1) | I55: =IF(L55>0,NbEch+Différé+1-H55,"") | J55: =IF(ISNUMBER(K55),YEAR(K55),"") | K55: =IF(L55=0,"",IF(Ijour=0,MIN(DATE(YEAR(DebAmort),MONTH(DebAmort)+(H55-1)*Imois,Jour1),DATE(YEAR(DebAmort),MONTH(DebAmort)+1+(H55-1)*Imois,0)),DATE(YEAR(DebAmort),MONTH(DebAmort),Jour1+(H55-1)*Ijour))) | L55: =L54-N54 | M55: =IF(H55<=NoEchMaxi,ROUND(L55*R55,NbDeci),0) | N55: =IF(OR(H55<=Différé,H55>NoEchMaxi),IF(DiffTotal,-M55,0),IF(H55>=NoEchRemb,L55,IF(S55-(M55*EchFIXE)>L55-2,L55,S55-(M55*EchFIXE))))+C55 | O55: =IF(OR(L55=0,H55>NoEchMaxi),0,ROUND(FraisF+FraisV*L55,NbDeci))+F55 | P55: =SUM(M55:O55) | R55: =IF(B55>0,IF(TauxActuariel,((B55+1)^(1/NbEchAn))-1,B55/NbEchAn),R54) | S55: =IF(E55>0,E55,IF(D55>0,IF(AND(EchFIXE,R55>0),ROUND((L55-C55)*R55/(1-((1+R55)^-D55)),NbDeci),ROUND(L55/D55,NbDeci)),S54))
H56: =IF(L56=0,"",H55+1) | I56: =IF(L56>0,NbEch+Différé+1-H56,"") | J56: =IF(ISNUMBER(K56),YEAR(K56),"") | K56: =IF(L56=0,"",IF(Ijour=0,MIN(DATE(YEAR(DebAmort),MONTH(DebAmort)+MoisD+(H56-1)*Imois,Jour2),DATE(YEAR(DebAmort),MONTH(DebAmort)+MoisD+1+(H56-1)*Imois,0)),DATE(YEAR(DebAmort),MONTH(DebAmort),Jour1+(H56-1)*Ijour))) | L56: =L55-N55 | M56: =IF(H56<=NoEchMaxi,ROUND(L56*R56,NbDeci),0) | N56: =IF(OR(H56<=Différé,H56>NoEchMaxi),IF(DiffTotal,-M56,0),IF(H56>=NoEchRemb,L56,IF(S56-(M56*EchFIXE)>L56-2,L56,S56-(M56*EchFIXE))))+C56 | O56: =IF(OR(L56=0,H56>NoEchMaxi),0,ROUND(FraisF+FraisV*L56,NbDeci))+F56 | P56: =SUM(M56:O56) | R56: =IF(B56>0,IF(TauxActuariel,((B56+1)^(1/NbEchAn))-1,B56/NbEchAn),R55) | S56: =IF(E56>0,E56,IF(D56>0,IF(AND(EchFIXE,R56>0),ROUND((L56-C56)*R56/(1-((1+R56)^-D56)),NbDeci),ROUND(L56/D56,NbDeci)),S55))
H57: =IF(L57=0,"",H56+1) | I57: =IF(L57>0,NbEch+Différé+1-H57,"") | J57: =IF(ISNUMBER(K57),YEAR(K57),"") | K57: =IF(L57=0,"",IF(Ijour=0,MIN(DATE(YEAR(DebAmort),MONTH(DebAmort)+(H57-1)*Imois,Jour1),DATE(YEAR(DebAmort),MONTH(DebAmort)+1+(H57-1)*Imois,0)),DATE(YEAR(DebAmort),MONTH(DebAmort),Jour1+(H57-1)*Ijour))) | L57: =L56-N56 | M57: =IF(H57<=NoEchMaxi,ROUND(L57*R57,NbDeci),0) | N57: =IF(OR(H57<=Différé,H57>NoEchMaxi),IF(DiffTotal,-M57,0),IF(H57>=NoEchRemb,L57,IF(S57-(M57*EchFIXE)>L57-2,L57,S57-(M57*EchFIXE))))+C57 | O57: =IF(OR(L57=0,H57>NoEchMaxi),0,ROUND(FraisF+FraisV*L57,NbDeci))+F57 | P57: =SUM(M57:O57) | R57: =IF(B57>0,IF(TauxActuariel,((B57+1)^(1/NbEchAn))-1,B57/NbEchAn),R56) | S57: =IF(E57>0,E57,IF(D57>0,IF(AND(EchFIXE,R57>0),ROUND((L57-C57)*R57/(1-((1+R57)^-D57)),NbDeci),ROUND(L57/D57,NbDeci)),S56))
H58: =IF(L58=0,"",H57+1) | I58: =IF(L58>0,NbEch+Différé+1-H58,"") | J58: =IF(ISNUMBER(K58),YEAR(K58),"") | K58: =IF(L58=0,"",IF(Ijour=0,MIN(DATE(YEAR(DebAmort),MONTH(DebAmort)+MoisD+(H58-1)*Imois,Jour2),DATE(YEAR(DebAmort),MONTH(DebAmort)+MoisD+1+(H58-1)*Imois,0)),DATE(YEAR(DebAmort),MONTH(DebAmort),Jour1+(H58-1)*Ijour))) | L58: =L57-N57 | M58: =IF(H58<=NoEchMaxi,ROUND(L58*R58,NbDeci),0) | N58: =IF(OR(H58<=Différé,H58>NoEchMaxi),IF(DiffTotal,-M58,0),IF(H58>=NoEchRemb,L58,IF(S58-(M58*EchFIXE)>L58-2,L58,S58-(M58*EchFIXE))))+C58 | O58: =IF(OR(L58=0,H58>NoEchMaxi),0,ROUND(FraisF+FraisV*L58,NbDeci))+F58 | P58: =SUM(M58:O58) | R58: =IF(B58>0,IF(TauxActuariel,((B58+1)^(1/NbEchAn))-1,B58/NbEchAn),R57) | S58: =IF(E58>0,E58,IF(D58>0,IF(AND(EchFIXE,R58>0),ROUND((L58-C58)*R58/(1-((1+R58)^-D58)),NbDeci),ROUND(L58/D58,NbDeci)),S57))
H59: =IF(L59=0,"",H58+1) | I59: =IF(L59>0,NbEch+Différé+1-H59,"") | J59: =IF(ISNUMBER(K59),YEAR(K59),"") | K59: =IF(L59=0,"",IF(Ijour=0,MIN(DATE(YEAR(DebAmort),MONTH(DebAmort)+(H59-1)*Imois,Jour1),DATE(YEAR(DebAmort),MONTH(DebAmort)+1+(H59-1)*Imois,0)),DATE(YEAR(DebAmort),MONTH(DebAmort),Jour1+(H59-1)*Ijour))) | L59: =L58-N58 | M59: =IF(H59<=NoEchMaxi,ROUND(L59*R59,NbDeci),0) | N59: =IF(OR(H59<=Différé,H59>NoEchMaxi),IF(DiffTotal,-M59,0),IF(H59>=NoEchRemb,L59,IF(S59-(M59*EchFIXE)>L59-2,L59,S59-(M59*EchFIXE))))+C59 | O59: =IF(OR(L59=0,H59>NoEchMaxi),0,ROUND(FraisF+FraisV*L59,NbDeci))+F59 | P59: =SUM(M59:O59) | R59: =IF(B59>0,IF(TauxActuariel,((B59+1)^(1/NbEchAn))-1,B59/NbEchAn),R58) | S59: =IF(E59>0,E59,IF(D59>0,IF(AND(EchFIXE,R59>0),ROUND((L59-C59)*R59/(1-((1+R59)^-D59)),NbDeci),ROUND(L59/D59,NbDeci)),S58))
H60: =IF(L60=0,"",H59+1) | I60: =IF(L60>0,NbEch+Différé+1-H60,"") | J60: =IF(ISNUMBER(K60),YEAR(K60),"") | K60: =IF(L60=0,"",IF(Ijour=0,MIN(DATE(YEAR(DebAmort),MONTH(DebAmort)+MoisD+(H60-1)*Imois,Jour2),DATE(YEAR(DebAmort),MONTH(DebAmort)+MoisD+1+(H60-1)*Imois,0)),DATE(YEAR(DebAmort),MONTH(DebAmort),Jour1+(H60-1)*Ijour))) | L60: =L59-N59 | M60: =IF(H60<=NoEchMaxi,ROUND(L60*R60,NbDeci),0) | N60: =IF(OR(H60<=Différé,H60>NoEchMaxi),IF(DiffTotal,-M60,0),IF(H60>=NoEchRemb,L60,IF(S60-(M60*EchFIXE)>L60-2,L60,S60-(M60*EchFIXE))))+C60 | O60: =IF(OR(L60=0,H60>NoEchMaxi),0,ROUND(FraisF+FraisV*L60,NbDeci))+F60 | P60: =SUM(M60:O60) | R60: =IF(B60>0,IF(TauxActuariel,((B60+1)^(1/NbEchAn))-1,B60/NbEchAn),R59) | S60: =IF(E60>0,E60,IF(D60>0,IF(AND(EchFIXE,R60>0),ROUND((L60-C60)*R60/(1-((1+R60)^-D60)),NbDeci),ROUND(L60/D60,NbDeci)),S59))
H61: =IF(L61=0,"",H60+1) | I61: =IF(L61>0,NbEch+Différé+1-H61,"") | J61: =IF(ISNUMBER(K61),YEAR(K61),"") | K61: =IF(L61=0,"",IF(Ijour=0,MIN(DATE(YEAR(DebAmort),MONTH(DebAmort)+(H61-1)*Imois,Jour1),DATE(YEAR(DebAmort),MONTH(DebAmort)+1+(H61-1)*Imois,0)),DATE(YEAR(DebAmort),MONTH(DebAmort),Jour1+(H61-1)*Ijour))) | L61: =L60-N60 | M61: =IF(H61<=NoEchMaxi,ROUND(L61*R61,NbDeci),0) | N61: =IF(OR(H61<=Différé,H61>NoEchMaxi),IF(DiffTotal,-M61,0),IF(H61>=NoEchRemb,L61,IF(S61-(M61*EchFIXE)>L61-2,L61,S61-(M61*EchFIXE))))+C61 | O61: =IF(OR(L61=0,H61>NoEchMaxi),0,ROUND(FraisF+FraisV*L61,NbDeci))+F61 | P61: =SUM(M61:O61) | R61: =IF(B61>0,IF(TauxActuariel,((B61+1)^(1/NbEchAn))-1,B61/NbEchAn),R60) | S61: =IF(E61>0,E61,IF(D61>0,IF(AND(EchFIXE,R61>0),ROUND((L61-C61)*R61/(1-((1+R61)^-D61)),NbDeci),ROUND(L61/D61,NbDeci)),S60))
H62: =IF(L62=0,"",H61+1) | I62: =IF(L62>0,NbEch+Différé+1-H62,"") | J62: =IF(ISNUMBER(K62),YEAR(K62),"") | K62: =IF(L62=0,"",IF(Ijour=0,MIN(DATE(YEAR(DebAmort),MONTH(DebAmort)+MoisD+(H62-1)*Imois,Jour2),DATE(YEAR(DebAmort),MONTH(DebAmort)+MoisD+1+(H62-1)*Imois,0)),DATE(YEAR(DebAmort),MONTH(DebAmort),Jour1+(H62-1)*Ijour))) | L62: =L61-N61 | M62: =IF(H62<=NoEchMaxi,ROUND(L62*R62,NbDeci),0) | N62: =IF(OR(H62<=Différé,H62>NoEchMaxi),IF(DiffTotal,-M62,0),IF(H62>=NoEchRemb,L62,IF(S62-(M62*EchFIXE)>L62-2,L62,S62-(M62*EchFIXE))))+C62 | O62: =IF(OR(L62=0,H62>NoEchMaxi),0,ROUND(FraisF+FraisV*L62,NbDeci))+F62 | P62: =SUM(M62:O62) | R62: =IF(B62>0,IF(TauxActuariel,((B62+1)^(1/NbEchAn))-1,B62/NbEchAn),R61) | S62: =IF(E62>0,E62,IF(D62>0,IF(AND(EchFIXE,R62>0),ROUND((L62-C62)*R62/(1-((1+R62)^-D62)),NbDeci),ROUND(L62/D62,NbDeci)),S61))
H63: =IF(L63=0,"",H62+1) | I63: =IF(L63>0,NbEch+Différé+1-H63,"") | J63: =IF(ISNUMBER(K63),YEAR(K63),"") | K63: =IF(L63=0,"",IF(Ijour=0,MIN(DATE(YEAR(DebAmort),MONTH(DebAmort)+(H63-1)*Imois,Jour1),DATE(YEAR(DebAmort),MONTH(DebAmort)+1+(H63-1)*Imois,0)),DATE(YEAR(DebAmort),MONTH(DebAmort),Jour1+(H63-1)*Ijour))) | L63: =L62-N62 | M63: =IF(H63<=NoEchMaxi,ROUND(L63*R63,NbDeci),0) | N63: =IF(OR(H63<=Différé,H63>NoEchMaxi),IF(DiffTotal,-M63,0),IF(H63>=NoEchRemb,L63,IF(S63-(M63*EchFIXE)>L63-2,L63,S63-(M63*EchFIXE))))+C63 | O63: =IF(OR(L63=0,H63>NoEchMaxi),0,ROUND(FraisF+FraisV*L63,NbDeci))+F63 | P63: =SUM(M63:O63) | R63: =IF(B63>0,IF(TauxActuariel,((B63+1)^(1/NbEchAn))-1,B63/NbEchAn),R62) | S63: =IF(E63>0,E63,IF(D63>0,IF(AND(EchFIXE,R63>0),ROUND((L63-C63)*R63/(1-((1+R63)^-D63)),NbDeci),ROUND(L63/D63,NbDeci)),S62))
H64: =IF(L64=0,"",H63+1) | I64: =IF(L64>0,NbEch+Différé+1-H64,"") | J64: =IF(ISNUMBER(K64),YEAR(K64),"") | K64: =IF(L64=0,"",IF(Ijour=0,MIN(DATE(YEAR(DebAmort),MONTH(DebAmort)+MoisD+(H64-1)*Imois,Jour2),DATE(YEAR(DebAmort),MONTH(DebAmort)+MoisD+1+(H64-1)*Imois,0)),DATE(YEAR(DebAmort),MONTH(DebAmort),Jour1+(H64-1)*Ijour))) | L64: =L63-N63 | M64: =IF(H64<=NoEchMaxi,ROUND(L64*R64,NbDeci),0) | N64: =IF(OR(H64<=Différé,H64>NoEchMaxi),IF(DiffTotal,-M64,0),IF(H64>=NoEchRemb,L64,IF(S64-(M64*EchFIXE)>L64-2,L64,S64-(M64*EchFIXE))))+C64 | O64: =IF(OR(L64=0,H64>NoEchMaxi),0,ROUND(FraisF+FraisV*L64,NbDeci))+F64 | P64: =SUM(M64:O64) | R64: =IF(B64>0,IF(TauxActuariel,((B64+1)^(1/NbEchAn))-1,B64/NbEchAn),R63) | S64: =IF(E64>0,E64,IF(D64>0,IF(AND(EchFIXE,R64>0),ROUND((L64-C64)*R64/(1-((1+R64)^-D64)),NbDeci),ROUND(L64/D64,NbDeci)),S63))
H65: =IF(L65=0,"",H64+1) | I65: =IF(L65>0,NbEch+Différé+1-H65,"") | J65: =IF(ISNUMBER(K65),YEAR(K65),"") | K65: =IF(L65=0,"",IF(Ijour=0,MIN(DATE(YEAR(DebAmort),MONTH(DebAmort)+(H65-1)*Imois,Jour1),DATE(YEAR(DebAmort),MONTH(DebAmort)+1+(H65-1)*Imois,0)),DATE(YEAR(DebAmort),MONTH(DebAmort),Jour1+(H65-1)*Ijour))) | L65: =L64-N64 | M65: =IF(H65<=NoEchMaxi,ROUND(L65*R65,NbDeci),0) | N65: =IF(OR(H65<=Différé,H65>NoEchMaxi),IF(DiffTotal,-M65,0),IF(H65>=NoEchRemb,L65,IF(S65-(M65*EchFIXE)>L65-2,L65,S65-(M65*EchFIXE))))+C65 | O65: =IF(OR(L65=0,H65>NoEchMaxi),0,ROUND(FraisF+FraisV*L65,NbDeci))+F65 | P65: =SUM(M65:O65) | R65: =IF(B65>0,IF(TauxActuariel,((B65+1)^(1/NbEchAn))-1,B65/NbEchAn),R64) | S65: =IF(E65>0,E65,IF(D65>0,IF(AND(EchFIXE,R65>0),ROUND((L65-C65)*R65/(1-((1+R65)^-D65)),NbDeci),ROUND(L65/D65,NbDeci)),S64))
H66: =IF(L66=0,"",H65+1) | I66: =IF(L66>0,NbEch+Différé+1-H66,"") | J66: =IF(ISNUMBER(K66),YEAR(K66),"") | K66: =IF(L66=0,"",IF(Ijour=0,MIN(DATE(YEAR(DebAmort),MONTH(DebAmort)+MoisD+(H66-1)*Imois,Jour2),DATE(YEAR(DebAmort),MONTH(DebAmort)+MoisD+1+(H66-1)*Imois,0)),DATE(YEAR(DebAmort),MONTH(DebAmort),Jour1+(H66-1)*Ijour))) | L66: =L65-N65 | M66: =IF(H66<=NoEchMaxi,ROUND(L66*R66,NbDeci),0) | N66: =IF(OR(H66<=Différé,H66>NoEchMaxi),IF(DiffTotal,-M66,0),IF(H66>=NoEchRemb,L66,IF(S66-(M66*EchFIXE)>L66-2,L66,S66-(M66*EchFIXE))))+C66 | O66: =IF(OR(L66=0,H66>NoEchMaxi),0,ROUND(FraisF+FraisV*L66,NbDeci))+F66 | P66: =SUM(M66:O66) | R66: =IF(B66>0,IF(TauxActuariel,((B66+1)^(1/NbEchAn))-1,B66/NbEchAn),R65) | S66: =IF(E66>0,E66,IF(D66>0,IF(AND(EchFIXE,R66>0),ROUND((L66-C66)*R66/(1-((1+R66)^-D66)),NbDeci),ROUND(L66/D66,NbDeci)),S65))
H67: =IF(L67=0,"",H66+1) | I67: =IF(L67>0,NbEch+Différé+1-H67,"") | J67: =IF(ISNUMBER(K67),YEAR(K67),"") | K67: =IF(L67=0,"",IF(Ijour=0,MIN(DATE(YEAR(DebAmort),MONTH(DebAmort)+(H67-1)*Imois,Jour1),DATE(YEAR(DebAmort),MONTH(DebAmort)+1+(H67-1)*Imois,0)),DATE(YEAR(DebAmort),MONTH(DebAmort),Jour1+(H67-1)*Ijour))) | L67: =L66-N66 | M67: =IF(H67<=NoEchMaxi,ROUND(L67*R67,NbDeci),0) | N67: =IF(OR(H67<=Différé,H67>NoEchMaxi),IF(DiffTotal,-M67,0),IF(H67>=NoEchRemb,L67,IF(S67-(M67*EchFIXE)>L67-2,L67,S67-(M67*EchFIXE))))+C67 | O67: =IF(OR(L67=0,H67>NoEchMaxi),0,ROUND(FraisF+FraisV*L67,NbDeci))+F67 | P67: =SUM(M67:O67) | R67: =IF(B67>0,IF(TauxActuariel,((B67+1)^(1/NbEchAn))-1,B67/NbEchAn),R66) | S67: =IF(E67>0,E67,IF(D67>0,IF(AND(EchFIXE,R67>0),ROUND((L67-C67)*R67/(1-((1+R67)^-D67)),NbDeci),ROUND(L67/D67,NbDeci)),S66))
H68: =IF(L68=0,"",H67+1) | I68: =IF(L68>0,NbEch+Différé+1-H68,"") | J68: =IF(ISNUMBER(K68),YEAR(K68),"") | K68: =IF(L68=0,"",IF(Ijour=0,MIN(DATE(YEAR(DebAmort),MONTH(DebAmort)+MoisD+(H68-1)*Imois,Jour2),DATE(YEAR(DebAmort),MONTH(DebAmort)+MoisD+1+(H68-1)*Imois,0)),DATE(YEAR(DebAmort),MONTH(DebAmort),Jour1+(H68-1)*Ijour))) | L68: =L67-N67 | M68: =IF(H68<=NoEchMaxi,ROUND(L68*R68,NbDeci),0) | N68: =IF(OR(H68<=Différé,H68>NoEchMaxi),IF(DiffTotal,-M68,0),IF(H68>=NoEchRemb,L68,IF(S68-(M68*EchFIXE)>L68-2,L68,S68-(M68*EchFIXE))))+C68 | O68: =IF(OR(L68=0,H68>NoEchMaxi),0,ROUND(FraisF+FraisV*L68,NbDeci))+F68 | P68: =SUM(M68:O68) | R68: =IF(B68>0,IF(TauxActuariel,((B68+1)^(1/NbEchAn))-1,B68/NbEchAn),R67) | S68: =IF(E68>0,E68,IF(D68>0,IF(AND(EchFIXE,R68>0),ROUND((L68-C68)*R68/(1-((1+R68)^-D68)),NbDeci),ROUND(L68/D68,NbDeci)),S67))
H69: =IF(L69=0,"",H68+1) | I69: =IF(L69>0,NbEch+Différé+1-H69,"") | J69: =IF(ISNUMBER(K69),YEAR(K69),"") | K69: =IF(L69=0,"",IF(Ijour=0,MIN(DATE(YEAR(DebAmort),MONTH(DebAmort)+(H69-1)*Imois,Jour1),DATE(YEAR(DebAmort),MONTH(DebAmort)+1+(H69-1)*Imois,0)),DATE(YEAR(DebAmort),MONTH(DebAmort),Jour1+(H69-1)*Ijour))) | L69: =L68-N68 | M69: =IF(H69<=NoEchMaxi,ROUND(L69*R69,NbDeci),0) | N69: =IF(OR(H69<=Différé,H69>NoEchMaxi),IF(DiffTotal,-M69,0),IF(H69>=NoEchRemb,L69,IF(S69-(M69*EchFIXE)>L69-2,L69,S69-(M69*EchFIXE))))+C69 | O69: =IF(OR(L69=0,H69>NoEchMaxi),0,ROUND(FraisF+FraisV*L69,NbDeci))+F69 | P69: =SUM(M69:O69) | R69: =IF(B69>0,IF(TauxActuariel,((B69+1)^(1/NbEchAn))-1,B69/NbEchAn),R68) | S69: =IF(E69>0,E69,IF(D69>0,IF(AND(EchFIXE,R69>0),ROUND((L69-C69)*R69/(1-((1+R69)^-D69)),NbDeci),ROUND(L69/D69,NbDeci)),S68))
H70: =IF(L70=0,"",H69+1) | I70: =IF(L70>0,NbEch+Différé+1-H70,"") | J70: =IF(ISNUMBER(K70),YEAR(K70),"") | K70: =IF(L70=0,"",IF(Ijour=0,MIN(DATE(YEAR(DebAmort),MONTH(DebAmort)+MoisD+(H70-1)*Imois,Jour2),DATE(YEAR(DebAmort),MONTH(DebAmort)+MoisD+1+(H70-1)*Imois,0)),DATE(YEAR(DebAmort),MONTH(DebAmort),Jour1+(H70-1)*Ijour))) | L70: =L69-N69 | M70: =IF(H70<=NoEchMaxi,ROUND(L70*R70,NbDeci),0) | N70: =IF(OR(H70<=Différé,H70>NoEchMaxi),IF(DiffTotal,-M70,0),IF(H70>=NoEchRemb,L70,IF(S70-(M70*EchFIXE)>L70-2,L70,S70-(M70*EchFIXE))))+C70 | O70: =IF(OR(L70=0,H70>NoEchMaxi),0,ROUND(FraisF+FraisV*L70,NbDeci))+F70 | P70: =SUM(M70:O70) | R70: =IF(B70>0,IF(TauxActuariel,((B70+1)^(1/NbEchAn))-1,B70/NbEchAn),R69) | S70: =IF(E70>0,E70,IF(D70>0,IF(AND(EchFIXE,R70>0),ROUND((L70-C70)*R70/(1-((1+R70)^-D70)),NbDeci),ROUND(L70/D70,NbDeci)),S69))
H71: =IF(L71=0,"",H70+1) | I71: =IF(L71>0,NbEch+Différé+1-H71,"") | J71: =IF(ISNUMBER(K71),YEAR(K71),"") | K71: =IF(L71=0,"",IF(Ijour=0,MIN(DATE(YEAR(DebAmort),MONTH(DebAmort)+(H71-1)*Imois,Jour1),DATE(YEAR(DebAmort),MONTH(DebAmort)+1+(H71-1)*Imois,0)),DATE(YEAR(DebAmort),MONTH(DebAmort),Jour1+(H71-1)*Ijour))) | L71: =L70-N70 | M71: =IF(H71<=NoEchMaxi,ROUND(L71*R71,NbDeci),0) | N71: =IF(OR(H71<=Différé,H71>NoEchMaxi),IF(DiffTotal,-M71,0),IF(H71>=NoEchRemb,L71,IF(S71-(M71*EchFIXE)>L71-2,L71,S71-(M71*EchFIXE))))+C71 | O71: =IF(OR(L71=0,H71>NoEchMaxi),0,ROUND(FraisF+FraisV*L71,NbDeci))+F71 | P71: =SUM(M71:O71) | R71: =IF(B71>0,IF(TauxActuariel,((B71+1)^(1/NbEchAn))-1,B71/NbEchAn),R70) | S71: =IF(E71>0,E71,IF(D71>0,IF(AND(EchFIXE,R71>0),ROUND((L71-C71)*R71/(1-((1+R71)^-D71)),NbDeci),ROUND(L71/D71,NbDeci)),S70))
H72: =IF(L72=0,"",H71+1) | I72: =IF(L72>0,NbEch+Différé+1-H72,"") | J72: =IF(ISNUMBER(K72),YEAR(K72),"") | K72: =IF(L72=0,"",IF(Ijour=0,MIN(DATE(YEAR(DebAmort),MONTH(DebAmort)+MoisD+(H72-1)*Imois,Jour2),DATE(YEAR(DebAmort),MONTH(DebAmort)+MoisD+1+(H72-1)*Imois,0)),DATE(YEAR(DebAmort),MONTH(DebAmort),Jour1+(H72-1)*Ijour))) | L72: =L71-N71 | M72: =IF(H72<=NoEchMaxi,ROUND(L72*R72,NbDeci),0) | N72: =IF(OR(H72<=Différé,H72>NoEchMaxi),IF(DiffTotal,-M72,0),IF(H72>=NoEchRemb,L72,IF(S72-(M72*EchFIXE)>L72-2,L72,S72-(M72*EchFIXE))))+C72 | O72: =IF(OR(L72=0,H72>NoEchMaxi),0,ROUND(FraisF+FraisV*L72,NbDeci))+F72 | P72: =SUM(M72:O72) | R72: =IF(B72>0,IF(TauxActuariel,((B72+1)^(1/NbEchAn))-1,B72/NbEchAn),R71) | S72: =IF(E72>0,E72,IF(D72>0,IF(AND(EchFIXE,R72>0),ROUND((L72-C72)*R72/(1-((1+R72)^-D72)),NbDeci),ROUND(L72/D72,NbDeci)),S71))
H73: =IF(L73=0,"",H72+1) | I73: =IF(L73>0,NbEch+Différé+1-H73,"") | J73: =IF(ISNUMBER(K73),YEAR(K73),"") | K73: =IF(L73=0,"",IF(Ijour=0,MIN(DATE(YEAR(DebAmort),MONTH(DebAmort)+(H73-1)*Imois,Jour1),DATE(YEAR(DebAmort),MONTH(DebAmort)+1+(H73-1)*Imois,0)),DATE(YEAR(DebAmort),MONTH(DebAmort),Jour1+(H73-1)*Ijour))) | L73: =L72-N72 | M73: =IF(H73<=NoEchMaxi,ROUND(L73*R73,NbDeci),0) | N73: =IF(OR(H73<=Différé,H73>NoEchMaxi),IF(DiffTotal,-M73,0),IF(H73>=NoEchRemb,L73,IF(S73-(M73*EchFIXE)>L73-2,L73,S73-(M73*EchFIXE))))+C73 | O73: =IF(OR(L73=0,H73>NoEchMaxi),0,ROUND(FraisF+FraisV*L73,NbDeci))+F73 | P73: =SUM(M73:O73) | R73: =IF(B73>0,IF(TauxActuariel,((B73+1)^(1/NbEchAn))-1,B73/NbEchAn),R72) | S73: =IF(E73>0,E73,IF(D73>0,IF(AND(EchFIXE,R73>0),ROUND((L73-C73)*R73/(1-((1+R73)^-D73)),NbDeci),ROUND(L73/D73,NbDeci)),S72))
H74: =IF(L74=0,"",H73+1) | I74: =IF(L74>0,NbEch+Différé+1-H74,"") | J74: =IF(ISNUMBER(K74),YEAR(K74),"") | K74: =IF(L74=0,"",IF(Ijour=0,MIN(DATE(YEAR(DebAmort),MONTH(DebAmort)+MoisD+(H74-1)*Imois,Jour2),DATE(YEAR(DebAmort),MONTH(DebAmort)+MoisD+1+(H74-1)*Imois,0)),DATE(YEAR(DebAmort),MONTH(DebAmort),Jour1+(H74-1)*Ijour))) | L74: =L73-N73 | M74: =IF(H74<=NoEchMaxi,ROUND(L74*R74,NbDeci),0) | N74: =IF(OR(H74<=Différé,H74>NoEchMaxi),IF(DiffTotal,-M74,0),IF(H74>=NoEchRemb,L74,IF(S74-(M74*EchFIXE)>L74-2,L74,S74-(M74*EchFIXE))))+C74 | O74: =IF(OR(L74=0,H74>NoEchMaxi),0,ROUND(FraisF+FraisV*L74,NbDeci))+F74 | P74: =SUM(M74:O74) | R74: =IF(B74>0,IF(TauxActuariel,((B74+1)^(1/NbEchAn))-1,B74/NbEchAn),R73) | S74: =IF(E74>0,E74,IF(D74>0,IF(AND(EchFIXE,R74>0),ROUND((L74-C74)*R74/(1-((1+R74)^-D74)),NbDeci),ROUND(L74/D74,NbDeci)),S73))
H75: =IF(L75=0,"",H74+1) | I75: =IF(L75>0,NbEch+Différé+1-H75,"") | J75: =IF(ISNUMBER(K75),YEAR(K75),"") | K75: =IF(L75=0,"",IF(Ijour=0,MIN(DATE(YEAR(DebAmort),MONTH(DebAmort)+(H75-1)*Imois,Jour1),DATE(YEAR(DebAmort),MONTH(DebAmort)+1+(H75-1)*Imois,0)),DATE(YEAR(DebAmort),MONTH(DebAmort),Jour1+(H75-1)*Ijour))) | L75: =L74-N74 | M75: =IF(H75<=NoEchMaxi,ROUND(L75*R75,NbDeci),0) | N75: =IF(OR(H75<=Différé,H75>NoEchMaxi),IF(DiffTotal,-M75,0),IF(H75>=NoEchRemb,L75,IF(S75-(M75*EchFIXE)>L75-2,L75,S75-(M75*EchFIXE))))+C75 | O75: =IF(OR(L75=0,H75>NoEchMaxi),0,ROUND(FraisF+FraisV*L75,NbDeci))+F75 | P75: =SUM(M75:O75) | R75: =IF(B75>0,IF(TauxActuariel,((B75+1)^(1/NbEchAn))-1,B75/NbEchAn),R74) | S75: =IF(E75>0,E75,IF(D75>0,IF(AND(EchFIXE,R75>0),ROUND((L75-C75)*R75/(1-((1+R75)^-D75)),NbDeci),ROUND(L75/D75,NbDeci)),S74))
H76: =IF(L76=0,"",H75+1) | I76: =IF(L76>0,NbEch+Différé+1-H76,"") | J76: =IF(ISNUMBER(K76),YEAR(K76),"") | K76: =IF(L76=0,"",IF(Ijour=0,MIN(DATE(YEAR(DebAmort),MONTH(DebAmort)+MoisD+(H76-1)*Imois,Jour2),DATE(YEAR(DebAmort),MONTH(DebAmort)+MoisD+1+(H76-1)*Imois,0)),DATE(YEAR(DebAmort),MONTH(DebAmort),Jour1+(H76-1)*Ijour))) | L76: =L75-N75 | M76: =IF(H76<=NoEchMaxi,ROUND(L76*R76,NbDeci),0) | N76: =IF(OR(H76<=Différé,H76>NoEchMaxi),IF(DiffTotal,-M76,0),IF(H76>=NoEchRemb,L76,IF(S76-(M76*EchFIXE)>L76-2,L76,S76-(M76*EchFIXE))))+C76 | O76: =IF(OR(L76=0,H76>NoEchMaxi),0,ROUND(FraisF+FraisV*L76,NbDeci))+F76 | P76: =SUM(M76:O76) | R76: =IF(B76>0,IF(TauxActuariel,((B76+1)^(1/NbEchAn))-1,B76/NbEchAn),R75) | S76: =IF(E76>0,E76,IF(D76>0,IF(AND(EchFIXE,R76>0),ROUND((L76-C76)*R76/(1-((1+R76)^-D76)),NbDeci),ROUND(L76/D76,NbDeci)),S75))
H77: =IF(L77=0,"",H76+1) | I77: =IF(L77>0,NbEch+Différé+1-H77,"") | J77: =IF(ISNUMBER(K77),YEAR(K77),"") | K77: =IF(L77=0,"",IF(Ijour=0,MIN(DATE(YEAR(DebAmort),MONTH(DebAmort)+(H77-1)*Imois,Jour1),DATE(YEAR(DebAmort),MONTH(DebAmort)+1+(H77-1)*Imois,0)),DATE(YEAR(DebAmort),MONTH(DebAmort),Jour1+(H77-1)*Ijour))) | L77: =L76-N76 | M77: =IF(H77<=NoEchMaxi,ROUND(L77*R77,NbDeci),0) | N77: =IF(OR(H77<=Différé,H77>NoEchMaxi),IF(DiffTotal,-M77,0),IF(H77>=NoEchRemb,L77,IF(S77-(M77*EchFIXE)>L77-2,L77,S77-(M77*EchFIXE))))+C77 | O77: =IF(OR(L77=0,H77>NoEchMaxi),0,ROUND(FraisF+FraisV*L77,NbDeci))+F77 | P77: =SUM(M77:O77) | R77: =IF(B77>0,IF(TauxActuariel,((B77+1)^(1/NbEchAn))-1,B77/NbEchAn),R76) | S77: =IF(E77>0,E77,IF(D77>0,IF(AND(EchFIXE,R77>0),ROUND((L77-C77)*R77/(1-((1+R77)^-D77)),NbDeci),ROUND(L77/D77,NbDeci)),S76))
H78: =IF(L78=0,"",H77+1) | I78: =IF(L78>0,NbEch+Différé+1-H78,"") | J78: =IF(ISNUMBER(K78),YEAR(K78),"") | K78: =IF(L78=0,"",IF(Ijour=0,MIN(DATE(YEAR(DebAmort),MONTH(DebAmort)+MoisD+(H78-1)*Imois,Jour2),DATE(YEAR(DebAmort),MONTH(DebAmort)+MoisD+1+(H78-1)*Imois,0)),DATE(YEAR(DebAmort),MONTH(DebAmort),Jour1+(H78-1)*Ijour))) | L78: =L77-N77 | M78: =IF(H78<=NoEchMaxi,ROUND(L78*R78,NbDeci),0) | N78: =IF(OR(H78<=Différé,H78>NoEchMaxi),IF(DiffTotal,-M78,0),IF(H78>=NoEchRemb,L78,IF(S78-(M78*EchFIXE)>L78-2,L78,S78-(M78*EchFIXE))))+C78 | O78: =IF(OR(L78=0,H78>NoEchMaxi),0,ROUND(FraisF+FraisV*L78,NbDeci))+F78 | P78: =SUM(M78:O78) | R78: =IF(B78>0,IF(TauxActuariel,((B78+1)^(1/NbEchAn))-1,B78/NbEchAn),R77) | S78: =IF(E78>0,E78,IF(D78>0,IF(AND(EchFIXE,R78>0),ROUND((L78-C78)*R78/(1-((1+R78)^-D78)),NbDeci),ROUND(L78/D78,NbDeci)),S77))
H79: =IF(L79=0,"",H78+1) | I79: =IF(L79>0,NbEch+Différé+1-H79,"") | J79: =IF(ISNUMBER(K79),YEAR(K79),"") | K79: =IF(L79=0,"",IF(Ijour=0,MIN(DATE(YEAR(DebAmort),MONTH(DebAmort)+(H79-1)*Imois,Jour1),DATE(YEAR(DebAmort),MONTH(DebAmort)+1+(H79-1)*Imois,0)),DATE(YEAR(DebAmort),MONTH(DebAmort),Jour1+(H79-1)*Ijour))) | L79: =L78-N78 | M79: =IF(H79<=NoEchMaxi,ROUND(L79*R79,NbDeci),0) | N79: =IF(OR(H79<=Différé,H79>NoEchMaxi),IF(DiffTotal,-M79,0),IF(H79>=NoEchRemb,L79,IF(S79-(M79*EchFIXE)>L79-2,L79,S79-(M79*EchFIXE))))+C79 | O79: =IF(OR(L79=0,H79>NoEchMaxi),0,ROUND(FraisF+FraisV*L79,NbDeci))+F79 | P79: =SUM(M79:O79) | R79: =IF(B79>0,IF(TauxActuariel,((B79+1)^(1/NbEchAn))-1,B79/NbEchAn),R78) | S79: =IF(E79>0,E79,IF(D79>0,IF(AND(EchFIXE,R79>0),ROUND((L79-C79)*R79/(1-((1+R79)^-D79)),NbDeci),ROUND(L79/D79,NbDeci)),S78))
H80: =IF(L80=0,"",H79+1) | I80: =IF(L80>0,NbEch+Différé+1-H80,"") | J80: =IF(ISNUMBER(K80),YEAR(K80),"") | K80: =IF(L80=0,"",IF(Ijour=0,MIN(DATE(YEAR(DebAmort),MONTH(DebAmort)+MoisD+(H80-1)*Imois,Jour2),DATE(YEAR(DebAmort),MONTH(DebAmort)+MoisD+1+(H80-1)*Imois,0)),DATE(YEAR(DebAmort),MONTH(DebAmort),Jour1+(H80-1)*Ijour))) | L80: =L79-N79 | M80: =IF(H80<=NoEchMaxi,ROUND(L80*R80,NbDeci),0) | N80: =IF(OR(H80<=Différé,H80>NoEchMaxi),IF(DiffTotal,-M80,0),IF(H80>=NoEchRemb,L80,IF(S80-(M80*EchFIXE)>L80-2,L80,S80-(M80*EchFIXE))))+C80 | O80: =IF(OR(L80=0,H80>NoEchMaxi),0,ROUND(FraisF+FraisV*L80,NbDeci))+F80 | P80: =SUM(M80:O80) | R80: =IF(B80>0,IF(TauxActuariel,((B80+1)^(1/NbEchAn))-1,B80/NbEchAn),R79) | S80: =IF(E80>0,E80,IF(D80>0,IF(AND(EchFIXE,R80>0),ROUND((L80-C80)*R80/(1-((1+R80)^-D80)),NbDeci),ROUND(L80/D80,NbDeci)),S79))
H81: =IF(L81=0,"",H80+1) | I81: =IF(L81>0,NbEch+Différé+1-H81,"") | J81: =IF(ISNUMBER(K81),YEAR(K81),"") | K81: =IF(L81=0,"",IF(Ijour=0,MIN(DATE(YEAR(DebAmort),MONTH(DebAmort)+(H81-1)*Imois,Jour1),DATE(YEAR(DebAmort),MONTH(DebAmort)+1+(H81-1)*Imois,0)),DATE(YEAR(DebAmort),MONTH(DebAmort),Jour1+(H81-1)*Ijour))) | L81: =L80-N80 | M81: =IF(H81<=NoEchMaxi,ROUND(L81*R81,NbDeci),0) | N81: =IF(OR(H81<=Différé,H81>NoEchMaxi),IF(DiffTotal,-M81,0),IF(H81>=NoEchRemb,L81,IF(S81-(M81*EchFIXE)>L81-2,L81,S81-(M81*EchFIXE))))+C81 | O81: =IF(OR(L81=0,H81>NoEchMaxi),0,ROUND(FraisF+FraisV*L81,NbDeci))+F81 | P81: =SUM(M81:O81) | R81: =IF(B81>0,IF(TauxActuariel,((B81+1)^(1/NbEchAn))-1,B81/NbEchAn),R80) | S81: =IF(E81>0,E81,IF(D81>0,IF(AND(EchFIXE,R81>0),ROUND((L81-C81)*R81/(1-((1+R81)^-D81)),NbDeci),ROUND(L81/D81,NbDeci)),S80))
H82: =IF(L82=0,"",H81+1) | I82: =IF(L82>0,NbEch+Différé+1-H82,"") | J82: =IF(ISNUMBER(K82),YEAR(K82),"") | K82: =IF(L82=0,"",IF(Ijour=0,MIN(DATE(YEAR(DebAmort),MONTH(DebAmort)+MoisD+(H82-1)*Imois,Jour2),DATE(YEAR(DebAmort),MONTH(DebAmort)+MoisD+1+(H82-1)*Imois,0)),DATE(YEAR(DebAmort),MONTH(DebAmort),Jour1+(H82-1)*Ijour))) | L82: =L81-N81 | M82: =IF(H82<=NoEchMaxi,ROUND(L82*R82,NbDeci),0) | N82: =IF(OR(H82<=Différé,H82>NoEchMaxi),IF(DiffTotal,-M82,0),IF(H82>=NoEchRemb,L82,IF(S82-(M82*EchFIXE)>L82-2,L82,S82-(M82*EchFIXE))))+C82 | O82: =IF(OR(L82=0,H82>NoEchMaxi),0,ROUND(FraisF+FraisV*L82,NbDeci))+F82 | P82: =SUM(M82:O82) | R82: =IF(B82>0,IF(TauxActuariel,((B82+1)^(1/NbEchAn))-1,B82/NbEchAn),R81) | S82: =IF(E82>0,E82,IF(D82>0,IF(AND(EchFIXE,R82>0),ROUND((L82-C82)*R82/(1-((1+R82)^-D82)),NbDeci),ROUND(L82/D82,NbDeci)),S81))
H83: =IF(L83=0,"",H82+1) | I83: =IF(L83>0,NbEch+Différé+1-H83,"") | J83: =IF(ISNUMBER(K83),YEAR(K83),"") | K83: =IF(L83=0,"",IF(Ijour=0,MIN(DATE(YEAR(DebAmort),MONTH(DebAmort)+(H83-1)*Imois,Jour1),DATE(YEAR(DebAmort),MONTH(DebAmort)+1+(H83-1)*Imois,0)),DATE(YEAR(DebAmort),MONTH(DebAmort),Jour1+(H83-1)*Ijour))) | L83: =L82-N82 | M83: =IF(H83<=NoEchMaxi,ROUND(L83*R83,NbDeci),0) | N83: =IF(OR(H83<=Différé,H83>NoEchMaxi),IF(DiffTotal,-M83,0),IF(H83>=NoEchRemb,L83,IF(S83-(M83*EchFIXE)>L83-2,L83,S83-(M83*EchFIXE))))+C83 | O83: =IF(OR(L83=0,H83>NoEchMaxi),0,ROUND(FraisF+FraisV*L83,NbDeci))+F83 | P83: =SUM(M83:O83) | R83: =IF(B83>0,IF(TauxActuariel,((B83+1)^(1/NbEchAn))-1,B83/NbEchAn),R82) | S83: =IF(E83>0,E83,IF(D83>0,IF(AND(EchFIXE,R83>0),ROUND((L83-C83)*R83/(1-((1+R83)^-D83)),NbDeci),ROUND(L83/D83,NbDeci)),S82))
H84: =IF(L84=0,"",H83+1) | I84: =IF(L84>0,NbEch+Différé+1-H84,"") | J84: =IF(ISNUMBER(K84),YEAR(K84),"") | K84: =IF(L84=0,"",IF(Ijour=0,MIN(DATE(YEAR(DebAmort),MONTH(DebAmort)+MoisD+(H84-1)*Imois,Jour2),DATE(YEAR(DebAmort),MONTH(DebAmort)+MoisD+1+(H84-1)*Imois,0)),DATE(YEAR(DebAmort),MONTH(DebAmort),Jour1+(H84-1)*Ijour))) | L84: =L83-N83 | M84: =IF(H84<=NoEchMaxi,ROUND(L84*R84,NbDeci),0) | N84: =IF(OR(H84<=Différé,H84>NoEchMaxi),IF(DiffTotal,-M84,0),IF(H84>=NoEchRemb,L84,IF(S84-(M84*EchFIXE)>L84-2,L84,S84-(M84*EchFIXE))))+C84 | O84: =IF(OR(L84=0,H84>NoEchMaxi),0,ROUND(FraisF+FraisV*L84,NbDeci))+F84 | P84: =SUM(M84:O84) | R84: =IF(B84>0,IF(TauxActuariel,((B84+1)^(1/NbEchAn))-1,B84/NbEchAn),R83) | S84: =IF(E84>0,E84,IF(D84>0,IF(AND(EchFIXE,R84>0),ROUND((L84-C84)*R84/(1-((1+R84)^-D84)),NbDeci),ROUND(L84/D84,NbDeci)),S83))
H85: =IF(L85=0,"",H84+1) | I85: =IF(L85>0,NbEch+Différé+1-H85,"") | J85: =IF(ISNUMBER(K85),YEAR(K85),"") | K85: =IF(L85=0,"",IF(Ijour=0,MIN(DATE(YEAR(DebAmort),MONTH(DebAmort)+(H85-1)*Imois,Jour1),DATE(YEAR(DebAmort),MONTH(DebAmort)+1+(H85-1)*Imois,0)),DATE(YEAR(DebAmort),MONTH(DebAmort),Jour1+(H85-1)*Ijour))) | L85: =L84-N84 | M85: =IF(H85<=NoEchMaxi,ROUND(L85*R85,NbDeci),0) | N85: =IF(OR(H85<=Différé,H85>NoEchMaxi),IF(DiffTotal,-M85,0),IF(H85>=NoEchRemb,L85,IF(S85-(M85*EchFIXE)>L85-2,L85,S85-(M85*EchFIXE))))+C85 | O85: =IF(OR(L85=0,H85>NoEchMaxi),0,ROUND(FraisF+FraisV*L85,NbDeci))+F85 | P85: =SUM(M85:O85) | R85: =IF(B85>0,IF(TauxActuariel,((B85+1)^(1/NbEchAn))-1,B85/NbEchAn),R84) | S85: =IF(E85>0,E85,IF(D85>0,IF(AND(EchFIXE,R85>0),ROUND((L85-C85)*R85/(1-((1+R85)^-D85)),NbDeci),ROUND(L85/D85,NbDeci)),S84))
H86: =IF(L86=0,"",H85+1) | I86: =IF(L86>0,NbEch+Différé+1-H86,"") | J86: =IF(ISNUMBER(K86),YEAR(K86),"") | K86: =IF(L86=0,"",IF(Ijour=0,MIN(DATE(YEAR(DebAmort),MONTH(DebAmort)+MoisD+(H86-1)*Imois,Jour2),DATE(YEAR(DebAmort),MONTH(DebAmort)+MoisD+1+(H86-1)*Imois,0)),DATE(YEAR(DebAmort),MONTH(DebAmort),Jour1+(H86-1)*Ijour))) | L86: =L85-N85 | M86: =IF(H86<=NoEchMaxi,ROUND(L86*R86,NbDeci),0) | N86: =IF(OR(H86<=Différé,H86>NoEchMaxi),IF(DiffTotal,-M86,0),IF(H86>=NoEchRemb,L86,IF(S86-(M86*EchFIXE)>L86-2,L86,S86-(M86*EchFIXE))))+C86 | O86: =IF(OR(L86=0,H86>NoEchMaxi),0,ROUND(FraisF+FraisV*L86,NbDeci))+F86 | P86: =SUM(M86:O86) | R86: =IF(B86>0,IF(TauxActuariel,((B86+1)^(1/NbEchAn))-1,B86/NbEchAn),R85) | S86: =IF(E86>0,E86,IF(D86>0,IF(AND(EchFIXE,R86>0),ROUND((L86-C86)*R86/(1-((1+R86)^-D86)),NbDeci),ROUND(L86/D86,NbDeci)),S85))
H87: =IF(L87=0,"",H86+1) | I87: =IF(L87>0,NbEch+Différé+1-H87,"") | J87: =IF(ISNUMBER(K87),YEAR(K87),"") | K87: =IF(L87=0,"",IF(Ijour=0,MIN(DATE(YEAR(DebAmort),MONTH(DebAmort)+(H87-1)*Imois,Jour1),DATE(YEAR(DebAmort),MONTH(DebAmort)+1+(H87-1)*Imois,0)),DATE(YEAR(DebAmort),MONTH(DebAmort),Jour1+(H87-1)*Ijour))) | L87: =L86-N86 | M87: =IF(H87<=NoEchMaxi,ROUND(L87*R87,NbDeci),0) | N87: =IF(OR(H87<=Différé,H87>NoEchMaxi),IF(DiffTotal,-M87,0),IF(H87>=NoEchRemb,L87,IF(S87-(M87*EchFIXE)>L87-2,L87,S87-(M87*EchFIXE))))+C87 | O87: =IF(OR(L87=0,H87>NoEchMaxi),0,ROUND(FraisF+FraisV*L87,NbDeci))+F87 | P87: =SUM(M87:O87) | R87: =IF(B87>0,IF(TauxActuariel,((B87+1)^(1/NbEchAn))-1,B87/NbEchAn),R86) | S87: =IF(E87>0,E87,IF(D87>0,IF(AND(EchFIXE,R87>0),ROUND((L87-C87)*R87/(1-((1+R87)^-D87)),NbDeci),ROUND(L87/D87,NbDeci)),S86))
H88: =IF(L88=0,"",H87+1) | I88: =IF(L88>0,NbEch+Différé+1-H88,"") | J88: =IF(ISNUMBER(K88),YEAR(K88),"") | K88: =IF(L88=0,"",IF(Ijour=0,MIN(DATE(YEAR(DebAmort),MONTH(DebAmort)+MoisD+(H88-1)*Imois,Jour2),DATE(YEAR(DebAmort),MONTH(DebAmort)+MoisD+1+(H88-1)*Imois,0)),DATE(YEAR(DebAmort),MONTH(DebAmort),Jour1+(H88-1)*Ijour))) | L88: =L87-N87 | M88: =IF(H88<=NoEchMaxi,ROUND(L88*R88,NbDeci),0) | N88: =IF(OR(H88<=Différé,H88>NoEchMaxi),IF(DiffTotal,-M88,0),IF(H88>=NoEchRemb,L88,IF(S88-(M88*EchFIXE)>L88-2,L88,S88-(M88*EchFIXE))))+C88 | O88: =IF(OR(L88=0,H88>NoEchMaxi),0,ROUND(FraisF+FraisV*L88,NbDeci))+F88 | P88: =SUM(M88:O88) | R88: =IF(B88>0,IF(TauxActuariel,((B88+1)^(1/NbEchAn))-1,B88/NbEchAn),R87) | S88: =IF(E88>0,E88,IF(D88>0,IF(AND(EchFIXE,R88>0),ROUND((L88-C88)*R88/(1-((1+R88)^-D88)),NbDeci),ROUND(L88/D88,NbDeci)),S87))
H89: =IF(L89=0,"",H88+1) | I89: =IF(L89>0,NbEch+Différé+1-H89,"") | J89: =IF(ISNUMBER(K89),YEAR(K89),"") | K89: =IF(L89=0,"",IF(Ijour=0,MIN(DATE(YEAR(DebAmort),MONTH(DebAmort)+(H89-1)*Imois,Jour1),DATE(YEAR(DebAmort),MONTH(DebAmort)+1+(H89-1)*Imois,0)),DATE(YEAR(DebAmort),MONTH(DebAmort),Jour1+(H89-1)*Ijour))) | L89: =L88-N88 | M89: =IF(H89<=NoEchMaxi,ROUND(L89*R89,NbDeci),0) | N89: =IF(OR(H89<=Différé,H89>NoEchMaxi),IF(DiffTotal,-M89,0),IF(H89>=NoEchRemb,L89,IF(S89-(M89*EchFIXE)>L89-2,L89,S89-(M89*EchFIXE))))+C89 | O89: =IF(OR(L89=0,H89>NoEchMaxi),0,ROUND(FraisF+FraisV*L89,NbDeci))+F89 | P89: =SUM(M89:O89) | R89: =IF(B89>0,IF(TauxActuariel,((B89+1)^(1/NbEchAn))-1,B89/NbEchAn),R88) | S89: =IF(E89>0,E89,IF(D89>0,IF(AND(EchFIXE,R89>0),ROUND((L89-C89)*R89/(1-((1+R89)^-D89)),NbDeci),ROUND(L89/D89,NbDeci)),S88))
H90: =IF(L90=0,"",H89+1) | I90: =IF(L90>0,NbEch+Différé+1-H90,"") | J90: =IF(ISNUMBER(K90),YEAR(K90),"") | K90: =IF(L90=0,"",IF(Ijour=0,MIN(DATE(YEAR(DebAmort),MONTH(DebAmort)+MoisD+(H90-1)*Imois,Jour2),DATE(YEAR(DebAmort),MONTH(DebAmort)+MoisD+1+(H90-1)*Imois,0)),DATE(YEAR(DebAmort),MONTH(DebAmort),Jour1+(H90-1)*Ijour))) | L90: =L89-N89 | M90: =IF(H90<=NoEchMaxi,ROUND(L90*R90,NbDeci),0) | N90: =IF(OR(H90<=Différé,H90>NoEchMaxi),IF(DiffTotal,-M90,0),IF(H90>=NoEchRemb,L90,IF(S90-(M90*EchFIXE)>L90-2,L90,S90-(M90*EchFIXE))))+C90 | O90: =IF(OR(L90=0,H90>NoEchMaxi),0,ROUND(FraisF+FraisV*L90,NbDeci))+F90 | P90: =SUM(M90:O90) | R90: =IF(B90>0,IF(TauxActuariel,((B90+1)^(1/NbEchAn))-1,B90/NbEchAn),R89) | S90: =IF(E90>0,E90,IF(D90>0,IF(AND(EchFIXE,R90>0),ROUND((L90-C90)*R90/(1-((1+R90)^-D90)),NbDeci),ROUND(L90/D90,NbDeci)),S89))
H91: =IF(L91=0,"",H90+1) | I91: =IF(L91>0,NbEch+Différé+1-H91,"") | J91: =IF(ISNUMBER(K91),YEAR(K91),"") | K91: =IF(L91=0,"",IF(Ijour=0,MIN(DATE(YEAR(DebAmort),MONTH(DebAmort)+(H91-1)*Imois,Jour1),DATE(YEAR(DebAmort),MONTH(DebAmort)+1+(H91-1)*Imois,0)),DATE(YEAR(DebAmort),MONTH(DebAmort),Jour1+(H91-1)*Ijour))) | L91: =L90-N90 | M91: =IF(H91<=NoEchMaxi,ROUND(L91*R91,NbDeci),0) | N91: =IF(OR(H91<=Différé,H91>NoEchMaxi),IF(DiffTotal,-M91,0),IF(H91>=NoEchRemb,L91,IF(S91-(M91*EchFIXE)>L91-2,L91,S91-(M91*EchFIXE))))+C91 | O91: =IF(OR(L91=0,H91>NoEchMaxi),0,ROUND(FraisF+FraisV*L91,NbDeci))+F91 | P91: =SUM(M91:O91) | R91: =IF(B91>0,IF(TauxActuariel,((B91+1)^(1/NbEchAn))-1,B91/NbEchAn),R90) | S91: =IF(E91>0,E91,IF(D91>0,IF(AND(EchFIXE,R91>0),ROUND((L91-C91)*R91/(1-((1+R91)^-D91)),NbDeci),ROUND(L91/D91,NbDeci)),S90))
H92: =IF(L92=0,"",H91+1) | I92: =IF(L92>0,NbEch+Différé+1-H92,"") | J92: =IF(ISNUMBER(K92),YEAR(K92),"") | K92: =IF(L92=0,"",IF(Ijour=0,MIN(DATE(YEAR(DebAmort),MONTH(DebAmort)+MoisD+(H92-1)*Imois,Jour2),DATE(YEAR(DebAmort),MONTH(DebAmort)+MoisD+1+(H92-1)*Imois,0)),DATE(YEAR(DebAmort),MONTH(DebAmort),Jour1+(H92-1)*Ijour))) | L92: =L91-N91 | M92: =IF(H92<=NoEchMaxi,ROUND(L92*R92,NbDeci),0) | N92: =IF(OR(H92<=Différé,H92>NoEchMaxi),IF(DiffTotal,-M92,0),IF(H92>=NoEchRemb,L92,IF(S92-(M92*EchFIXE)>L92-2,L92,S92-(M92*EchFIXE))))+C92 | O92: =IF(OR(L92=0,H92>NoEchMaxi),0,ROUND(FraisF+FraisV*L92,NbDeci))+F92 | P92: =SUM(M92:O92) | R92: =IF(B92>0,IF(TauxActuariel,((B92+1)^(1/NbEchAn))-1,B92/NbEchAn),R91) | S92: =IF(E92>0,E92,IF(D92>0,IF(AND(EchFIXE,R92>0),ROUND((L92-C92)*R92/(1-((1+R92)^-D92)),NbDeci),ROUND(L92/D92,NbDeci)),S91))
H93: =IF(L93=0,"",H92+1) | I93: =IF(L93>0,NbEch+Différé+1-H93,"") | J93: =IF(ISNUMBER(K93),YEAR(K93),"") | K93: =IF(L93=0,"",IF(Ijour=0,MIN(DATE(YEAR(DebAmort),MONTH(DebAmort)+(H93-1)*Imois,Jour1),DATE(YEAR(DebAmort),MONTH(DebAmort)+1+(H93-1)*Imois,0)),DATE(YEAR(DebAmort),MONTH(DebAmort),Jour1+(H93-1)*Ijour))) | L93: =L92-N92 | M93: =IF(H93<=NoEchMaxi,ROUND(L93*R93,NbDeci),0) | N93: =IF(OR(H93<=Différé,H93>NoEchMaxi),IF(DiffTotal,-M93,0),IF(H93>=NoEchRemb,L93,IF(S93-(M93*EchFIXE)>L93-2,L93,S93-(M93*EchFIXE))))+C93 | O93: =IF(OR(L93=0,H93>NoEchMaxi),0,ROUND(FraisF+FraisV*L93,NbDeci))+F93 | P93: =SUM(M93:O93) | R93: =IF(B93>0,IF(TauxActuariel,((B93+1)^(1/NbEchAn))-1,B93/NbEchAn),R92) | S93: =IF(E93>0,E93,IF(D93>0,IF(AND(EchFIXE,R93>0),ROUND((L93-C93)*R93/(1-((1+R93)^-D93)),NbDeci),ROUND(L93/D93,NbDeci)),S92))
H94: =IF(L94=0,"",H93+1) | I94: =IF(L94>0,NbEch+Différé+1-H94,"") | J94: =IF(ISNUMBER(K94),YEAR(K94),"") | K94: =IF(L94=0,"",IF(Ijour=0,MIN(DATE(YEAR(DebAmort),MONTH(DebAmort)+MoisD+(H94-1)*Imois,Jour2),DATE(YEAR(DebAmort),MONTH(DebAmort)+MoisD+1+(H94-1)*Imois,0)),DATE(YEAR(DebAmort),MONTH(DebAmort),Jour1+(H94-1)*Ijour))) | L94: =L93-N93 | M94: =IF(H94<=NoEchMaxi,ROUND(L94*R94,NbDeci),0) | N94: =IF(OR(H94<=Différé,H94>NoEchMaxi),IF(DiffTotal,-M94,0),IF(H94>=NoEchRemb,L94,IF(S94-(M94*EchFIXE)>L94-2,L94,S94-(M94*EchFIXE))))+C94 | O94: =IF(OR(L94=0,H94>NoEchMaxi),0,ROUND(FraisF+FraisV*L94,NbDeci))+F94 | P94: =SUM(M94:O94) | R94: =IF(B94>0,IF(TauxActuariel,((B94+1)^(1/NbEchAn))-1,B94/NbEchAn),R93) | S94: =IF(E94>0,E94,IF(D94>0,IF(AND(EchFIXE,R94>0),ROUND((L94-C94)*R94/(1-((1+R94)^-D94)),NbDeci),ROUND(L94/D94,NbDeci)),S93))
H95: =IF(L95=0,"",H94+1) | I95: =IF(L95>0,NbEch+Différé+1-H95,"") | J95: =IF(ISNUMBER(K95),YEAR(K95),"") | K95: =IF(L95=0,"",IF(Ijour=0,MIN(DATE(YEAR(DebAmort),MONTH(DebAmort)+(H95-1)*Imois,Jour1),DATE(YEAR(DebAmort),MONTH(DebAmort)+1+(H95-1)*Imois,0)),DATE(YEAR(DebAmort),MONTH(DebAmort),Jour1+(H95-1)*Ijour))) | L95: =L94-N94 | M95: =IF(H95<=NoEchMaxi,ROUND(L95*R95,NbDeci),0) | N95: =IF(OR(H95<=Différé,H95>NoEchMaxi),IF(DiffTotal,-M95,0),IF(H95>=NoEchRemb,L95,IF(S95-(M95*EchFIXE)>L95-2,L95,S95-(M95*EchFIXE))))+C95 | O95: =IF(OR(L95=0,H95>NoEchMaxi),0,ROUND(FraisF+FraisV*L95,NbDeci))+F95 | P95: =SUM(M95:O95) | R95: =IF(B95>0,IF(TauxActuariel,((B95+1)^(1/NbEchAn))-1,B95/NbEchAn),R94) | S95: =IF(E95>0,E95,IF(D95>0,IF(AND(EchFIXE,R95>0),ROUND((L95-C95)*R95/(1-((1+R95)^-D95)),NbDeci),ROUND(L95/D95,NbDeci)),S94))
H96: =IF(L96=0,"",H95+1) | I96: =IF(L96>0,NbEch+Différé+1-H96,"") | J96: =IF(ISNUMBER(K96),YEAR(K96),"") | K96: =IF(L96=0,"",IF(Ijour=0,MIN(DATE(YEAR(DebAmort),MONTH(DebAmort)+MoisD+(H96-1)*Imois,Jour2),DATE(YEAR(DebAmort),MONTH(DebAmort)+MoisD+1+(H96-1)*Imois,0)),DATE(YEAR(DebAmort),MONTH(DebAmort),Jour1+(H96-1)*Ijour))) | L96: =L95-N95 | M96: =IF(H96<=NoEchMaxi,ROUND(L96*R96,NbDeci),0) | N96: =IF(OR(H96<=Différé,H96>NoEchMaxi),IF(DiffTotal,-M96,0),IF(H96>=NoEchRemb,L96,IF(S96-(M96*EchFIXE)>L96-2,L96,S96-(M96*EchFIXE))))+C96 | O96: =IF(OR(L96=0,H96>NoEchMaxi),0,ROUND(FraisF+FraisV*L96,NbDeci))+F96 | P96: =SUM(M96:O96) | R96: =IF(B96>0,IF(TauxActuariel,((B96+1)^(1/NbEchAn))-1,B96/NbEchAn),R95) | S96: =IF(E96>0,E96,IF(D96>0,IF(AND(EchFIXE,R96>0),ROUND((L96-C96)*R96/(1-((1+R96)^-D96)),NbDeci),ROUND(L96/D96,NbDeci)),S95))
H97: =IF(L97=0,"",H96+1) | I97: =IF(L97>0,NbEch+Différé+1-H97,"") | J97: =IF(ISNUMBER(K97),YEAR(K97),"") | K97: =IF(L97=0,"",IF(Ijour=0,MIN(DATE(YEAR(DebAmort),MONTH(DebAmort)+(H97-1)*Imois,Jour1),DATE(YEAR(DebAmort),MONTH(DebAmort)+1+(H97-1)*Imois,0)),DATE(YEAR(DebAmort),MONTH(DebAmort),Jour1+(H97-1)*Ijour))) | L97: =L96-N96 | M97: =IF(H97<=NoEchMaxi,ROUND(L97*R97,NbDeci),0) | N97: =IF(OR(H97<=Différé,H97>NoEchMaxi),IF(DiffTotal,-M97,0),IF(H97>=NoEchRemb,L97,IF(S97-(M97*EchFIXE)>L97-2,L97,S97-(M97*EchFIXE))))+C97 | O97: =IF(OR(L97=0,H97>NoEchMaxi),0,ROUND(FraisF+FraisV*L97,NbDeci))+F97 | P97: =SUM(M97:O97) | R97: =IF(B97>0,IF(TauxActuariel,((B97+1)^(1/NbEchAn))-1,B97/NbEchAn),R96) | S97: =IF(E97>0,E97,IF(D97>0,IF(AND(EchFIXE,R97>0),ROUND((L97-C97)*R97/(1-((1+R97)^-D97)),NbDeci),ROUND(L97/D97,NbDeci)),S96))
H98: =IF(L98=0,"",H97+1) | I98: =IF(L98>0,NbEch+Différé+1-H98,"") | J98: =IF(ISNUMBER(K98),YEAR(K98),"") | K98: =IF(L98=0,"",IF(Ijour=0,MIN(DATE(YEAR(DebAmort),MONTH(DebAmort)+MoisD+(H98-1)*Imois,Jour2),DATE(YEAR(DebAmort),MONTH(DebAmort)+MoisD+1+(H98-1)*Imois,0)),DATE(YEAR(DebAmort),MONTH(DebAmort),Jour1+(H98-1)*Ijour))) | L98: =L97-N97 | M98: =IF(H98<=NoEchMaxi,ROUND(L98*R98,NbDeci),0) | N98: =IF(OR(H98<=Différé,H98>NoEchMaxi),IF(DiffTotal,-M98,0),IF(H98>=NoEchRemb,L98,IF(S98-(M98*EchFIXE)>L98-2,L98,S98-(M98*EchFIXE))))+C98 | O98: =IF(OR(L98=0,H98>NoEchMaxi),0,ROUND(FraisF+FraisV*L98,NbDeci))+F98 | P98: =SUM(M98:O98) | R98: =IF(B98>0,IF(TauxActuariel,((B98+1)^(1/NbEchAn))-1,B98/NbEchAn),R97) | S98: =IF(E98>0,E98,IF(D98>0,IF(AND(EchFIXE,R98>0),ROUND((L98-C98)*R98/(1-((1+R98)^-D98)),NbDeci),ROUND(L98/D98,NbDeci)),S97))
H99: =IF(L99=0,"",H98+1) | I99: =IF(L99>0,NbEch+Différé+1-H99,"") | J99: =IF(ISNUMBER(K99),YEAR(K99),"") | K99: =IF(L99=0,"",IF(Ijour=0,MIN(DATE(YEAR(DebAmort),MONTH(DebAmort)+(H99-1)*Imois,Jour1),DATE(YEAR(DebAmort),MONTH(DebAmort)+1+(H99-1)*Imois,0)),DATE(YEAR(DebAmort),MONTH(DebAmort),Jour1+(H99-1)*Ijour))) | L99: =L98-N98 | M99: =IF(H99<=NoEchMaxi,ROUND(L99*R99,NbDeci),0) | N99: =IF(OR(H99<=Différé,H99>NoEchMaxi),IF(DiffTotal,-M99,0),IF(H99>=NoEchRemb,L99,IF(S99-(M99*EchFIXE)>L99-2,L99,S99-(M99*EchFIXE))))+C99 | O99: =IF(OR(L99=0,H99>NoEchMaxi),0,ROUND(FraisF+FraisV*L99,NbDeci))+F99 | P99: =SUM(M99:O99) | R99: =IF(B99>0,IF(TauxActuariel,((B99+1)^(1/NbEchAn))-1,B99/NbEchAn),R98) | S99: =IF(E99>0,E99,IF(D99>0,IF(AND(EchFIXE,R99>0),ROUND((L99-C99)*R99/(1-((1+R99)^-D99)),NbDeci),ROUND(L99/D99,NbDeci)),S98))
H100: =IF(L100=0,"",H99+1) | I100: =IF(L100>0,NbEch+Différé+1-H100,"") | J100: =IF(ISNUMBER(K100),YEAR(K100),"") | K100: =IF(L100=0,"",IF(Ijour=0,MIN(DATE(YEAR(DebAmort),MONTH(DebAmort)+MoisD+(H100-1)*Imois,Jour2),DATE(YEAR(DebAmort),MONTH(DebAmort)+MoisD+1+(H100-1)*Imois,0)),DATE(YEAR(DebAmort),MONTH(DebAmort),Jour1+(H100-1)*Ijour))) | L100: =L99-N99 | M100: =IF(H100<=NoEchMaxi,ROUND(L100*R100,NbDeci),0) | N100: =IF(OR(H100<=Différé,H100>NoEchMaxi),IF(DiffTotal,-M100,0),IF(H100>=NoEchRemb,L100,IF(S100-(M100*EchFIXE)>L100-2,L100,S100-(M100*EchFIXE))))+C100 | O100: =IF(OR(L100=0,H100>NoEchMaxi),0,ROUND(FraisF+FraisV*L100,NbDeci))+F100 | P100: =SUM(M100:O100) | R100: =IF(B100>0,IF(TauxActuariel,((B100+1)^(1/NbEchAn))-1,B100/NbEchAn),R99) | S100: =IF(E100>0,E100,IF(D100>0,IF(AND(EchFIXE,R100>0),ROUND((L100-C100)*R100/(1-((1+R100)^-D100)),NbDeci),ROUND(L100/D100,NbDeci)),S99))
...

Sheet Avancé
I1: Colonne
B2: Décimalisation de la monnaie | I2: Non
B3: Nombre de décimales | D3: 3 | I3: Verouillé
I4: (A CACHER)
B5: Type d'amortissement
I9: 1
B11: Limitation de l'amortissement
I12: FALSE
C14: à | E14: an(s) et / ou | G14: mois
I15: FALSE
D17: =IF(I12=TRUE,(D14*12+F14)*NbEchAn/12,99999) | E17: =IF(AND(I12,I15),(D14*12+F14)*NbEchAn/12,99999)
B19: Calcul première échéance
B21: Date première échéance : | D21: =DebAmort
B22: Date déblocage théorique : | D22: =IF(Ijour=0,MIN(DATE(YEAR(DebAmort),MONTH(DebAmort)-MoisD-Imois,Jour2),DATE(YEAR(DebAmort),MONTH(DebAmort)-MoisD+1-Imois,0)),DATE(YEAR(DebAmort),MONTH(DebAmort),Jour1-Ijour)) | E22: =" (Durée période : "&F37&" jours)"
B23: Date déblocage réel : | D23: =D22+I23-500 | E23: =" (Durée période : "&G37&" jours)" | I23: 500
I27: 1
D32: -1- | E32: -2- | F32: -3-
B33: Date déblocage fonds : | D33: =D22 | E33: =D23 | F33: =D23
B34: Montant des Intérêts : | D34: =ROUND(TAM!L15*TAM!R15,NbDeci) | E34: =IF(TauxActuariel, ROUND(TAM!L15*(((TAM!D5+1)^(G37/365))-1),NbDeci), ROUND(TAM!L15*(TAM!D5*G37/365),NbDeci))
B35: Montant du capital : | D35: =IF(1<=Différé,IF(DiffTotal,-D34,0),TAM!S15-(D34*EchFIXE)) | E35: =IF(AND(1<=Différé,DiffTotal),-E34,D35)
B36: Total échéance (hors frais) : | D36: =D34+D35 | E36: =E34+E35 | F36: =F34+F35
C37: =IF(I27=1,D22,D23) | D37: =IF(I27=1,D34)+IF(I27=2,E34)+IF(I27=3,F34) | E37: =IF(I27=1,D35)+IF(I27=2,E35)+IF(I27=3,F35) | F37: =D21-D22 | G37: =D21-D23
